Workbook

Sheet feedback elearning
A1: Timestamp | B1: Tên của bạn | C1: Đánh giá trải nghiệm của bạn với khóa Thuyết trình hiệu quả [Trải nghiệm chung] | D1: Đánh giá trải nghiệm của bạn với khóa Thuyết trình hiệu quả [Mức độ hài lòng với nội dung?] | E1: Đánh giá trải nghiệm của bạn với khóa Thuyết trình hiệu quả [Mức độ hài lòng với hình thức khóa E-learning? (VD: nội dung minh họa, tương tác, câu hỏi, bài quiz,...)] | F1: Đánh giá trải nghiệm của bạn với khóa Thuyết trình hiệu quả [Mức độ hài lòng với truyền thông và hỗ trợ của Bộ phận đào tạo?] | G1: Đánh giá trải nghiệm của bạn với khóa No-code Automation [Trải nghiệm chung] | H1: Đánh giá trải nghiệm của bạn với khóa No-code Automation [Mức độ hài lòng với nội dung?] | I1: Đánh giá trải nghiệm của bạn với khóa No-code Automation [Mức độ hài lòng với hình thức khóa E-learning? (VD: nội dung minh họa, tương tác, câu hỏi, bài quiz,...)] | J1: Đánh giá trải nghiệm của bạn với khóa No-code Automation [Mức độ hài lòng với truyền thông và hỗ trợ của Bộ phận đào tạo?] | K1: Đánh giá trải nghiệm của bạn với khóa Sắp xếp ưu tiên và quản trị công việc hiệu quả [Trải nghiệm chung] | L1: Đánh giá trải nghiệm của bạn với khóa Sắp xếp ưu tiên và quản trị công việc hiệu quả [Mức độ hài lòng với nội dung?] | M1: Đánh giá trải nghiệm của bạn với khóa Sắp xếp ưu tiên và quản trị công việc hiệu quả [Mức độ hài lòng với hình thức khóa E-learning? (VD: nội dung minh họa, tương tác, câu hỏi, bài quiz,...)] | N1: Đánh giá trải nghiệm của bạn với khóa Sắp xếp ưu tiên và quản trị công việc hiệu quả [Mức độ hài lòng với truyền thông và hỗ trợ của Bộ phận đào tạo?] | O1: Vui lòng chia sẻ một điều mà bạn học được và có thể áp dụng trong thực tế công việc thông qua các khóa học này? (tùy chọn trả lời) | P1: Vui lòng chia sẻ thêm các phản hồi /gợi ý khác của bạn để cải thiện chất lượng đào tạo? (tùy chọn trả lời)
A2: 46020.738 | B2: Trần Cao Cương | C2: NA - Tôi chưa học khóa này | D2: NA - Tôi chưa học khóa này | E2: NA - Tôi chưa học khóa này | F2: NA - Tôi chưa học khóa này | G2: NA - Tôi chưa học khóa này | H2: NA - Tôi chưa học khóa này | I2: NA - Tôi chưa học khóa này | J2: NA - Tôi chưa học khóa này | K2: 5 | L2: 5 | M2: 5 | N2: 5
A3: 46021.494 | B3: Mai Anh Tuấn | C3: 5 | D3: 5 | E3: 5 | F3: 5 | G3: 5 | H3: 5 | I3: 5 | J3: 5 | K3: 5 | L3: 5 | M3: 5 | N3: 5 | O3: Thuyết trình hiệu quả, trình bày slide hợp lý
A4: 46021.659 | B4: Nhi | C4: 4 | D4: 4 | E4: 4 | F4: 4 | G4: NA - Tôi chưa học khóa này | H4: NA - Tôi chưa học khóa này | I4: NA - Tôi chưa học khóa này | J4: NA - Tôi chưa học khóa này | K4: 4 | L4: 4 | M4: 4 | N4: 4 | O4: Tôi tự xắp xếp thứ tự công việc ưu tiên để không bị chậm dealine | P4: NA
A5: 46021.761 | B5: NGUYEN THI LOAN | C5: 4 | D5: 4 | E5: 4 | F5: 4 | G5: 4 | H5: 4 | I5: 4 | J5: 4 | K5: 4 | L5: 4 | M5: 4 | N5: 4
A6: 46021.778 | B6: Lương Thị Thuý Quỳnh | C6: 5 | D6: 5 | E6: 5 | F6: 5 | G6: 5 | H6: 5 | I6: 5 | J6: 5 | K6: 5 | L6: 5 | M6: 5 | N6: 5
A7: 46022.367 | B7: Trần Thu Trang | C7: 5 | D7: 5 | E7: 5 | F7: 5 | G7: 5 | H7: 5 | I7: 5 | J7: 5 | K7: 5 | L7: 5 | M7: 5 | N7: 5
A8: 46022.384 | B8: Nguyễn Thu Trang | C8: 4 | D8: 4 | E8: 4 | F8: 4 | G8: NA - Tôi chưa học khóa này | H8: NA - Tôi chưa học khóa này | I8: NA - Tôi chưa học khóa này | J8: NA - Tôi chưa học khóa này | K8: 4 | L8: 4 | M8: 4 | N8: 4
A9: 46022.412 | B9: Trần Thu Giang | C9: NA - Tôi chưa học khóa này | D9: NA - Tôi chưa học khóa này | E9: NA - Tôi chưa học khóa này | F9: NA - Tôi chưa học khóa này | G9: 4 | H9: 3 | I9: 3 | J9: 4 | K9: NA - Tôi chưa học khóa này | L9: NA - Tôi chưa học khóa này | M9: NA - Tôi chưa học khóa này | N9: NA - Tôi chưa học khóa này | O9: Biết được một số term để tự tìm hiểu khi làm no-code automation
A10: 46022.414 | B10: The Anh | C10: NA - Tôi chưa học khóa này | D10: NA - Tôi chưa học khóa này | E10: NA - Tôi chưa học khóa này | F10: NA - Tôi chưa học khóa này | G10: 5 | H10: 5 | I10: 5 | J10: 5 | K10: NA - Tôi chưa học khóa này | L10: NA - Tôi chưa học khóa này | M10: NA - Tôi chưa học khóa này | N10: NA - Tôi chưa học khóa này
A11: 46024.428 | B11: Nguyễn Thị Thu Trang | C11: 5 | D11: 5 | E11: 5 | F11: 5 | G11: 5 | H11: 5 | I11: 5 | J11: 5 | K11: 5 | L11: 5 | M11: 5 | N11: 5
A12: 46044.769 | B12: Ngô Thành Trung | C12: 4 | D12: 5 | E12: 5 | F12: 5 | G12: 4 | H12: 4 | I12: 4 | J12: 5 | K12: 5 | L12: 5 | M12: 5 | N12: 5 | O12: Áp dụng trực tiếp vào công việc rất tốt | P12: Khóa nào em cũng hài lòng về nội dung nhưng có khóa em chấm 4 điểm là do còn lỗi chính tả, em nghĩ mình có thể khắc phục ạ
B13: Thân Việt Anh | P13: Hình thức online e thấy hơi thiếu tương tác, kiểu bị 1 chiều bị thiếu phần discussion so với học offline Góp ý thì chắc là ở dạng meeting e nghĩ có thể hiệu quả hơn UI UX thì ok e k gặp vấn đề gì E thấy tương đối ok, cơ mà phần đầu khá nặng lí thuyết Hơi dài, chắc nên thiên về practical case hơn r tự mình ngẫm có fit với công ty k, kiểu học lí thuyết thì hơi giống hồi học ĐH Nếu ở dạng meeting và về mảng muốn học thêm thì e sẵn lòng
B14: Mai Anh Tuấn | P14: Hình thức học tương đối hiệu quả, sinh động, rất thích khi có phần quà được trao Góp ý: Mong muốn có thêm hình thức thực hành, và mong muốn mở rộng thêm các khóa học chuyên sâu về team của mình, ví dụ như em là team product thì em rất muốn nghe các khóa học đến từ các anh bên product, nói về users, revenue, events, ... và các ứng dụng AI thực tế vào công việc của product Nội dung khóa học vô cùng hữu ích Thiết kế bài học hay quiz rất dễ hiểu, site làm tương đối thuận flow khi đọc Rất mong muốn có thêm những bài học tương tự trong tương lại :>
B15: Nguyễn Văn Hoàng | P15: Em thấy học Elearning này khá là hay nhưng mà nó đang chưa giống việc học lắm, hoặc là em thấy nó chưa có impact với em về mảng em muốn học. Các khóa này có thể có ích với người khác thì em chưa rõ. theo cá nhân em đã trải qua 1 khóa elearning em thấy nó chưa thật sự cần thiết với em lắm, khóa đó em học nhằm mục đích tìm hiểu xem như thế nào là chính. ** Mong muốn của em sẽ được mở rộng khóa học với nhiều nội dung hơn ví dụ: khóa học prompt ai, khóa học alpha inteligent hoặc học về alpha knowledge, khóa học về clip.ingarena,toogen ... gì đó sẽ có ích với em hơn. Các khóa học nên có lộ trình dài hơn có thể là vài tháng hoặc vài tuần gì đó. mỗi ngày 2 tiếng hoặc ít hơn. (cái này do em hardcore còn người khác em không rõ :(( ) Nếu có khóa học về lập trình hoặc gì gì đó về kỹ năng hơn sẽ tốt hơn ạ. Em mong muốn có một khóa về tiếng anh bổ túc cho mọi người sẽ hợp lý. Em thấy có nhiều người em làm việc cùng không có tốt về tiếng Anh cho lắm.
B16: Đặng Minh Tuấn | P16: 1/ Mình thấy hình thức này học tiện lợi vì khi rảnh có thể học mọi lúc mà không bị gò bó 2/ Hiện tại thì không có gì khó khăn vì cơ bản đã từng thử nghiệm trên đó 3/ Nội dung khóa rất thực tế, giúp mình tự động hóa được vài task thủ công trong công việc cũng như việc cá nhân 4/ Thiết kế Slide rõ ràng, dễ hiểu. Phần Quiz nên thêm các tình huống "va chạm" :))) 5/ Có muốn học thêm theo hình thức này để có thể biết thêm về nhiều khía cạnh khác các tips để sup cho công việc vì không có thời gian rãnh để học cố định.
B17: Nguyễn Anh Khoa | P17: Nhanh gọn lẹ, hình thức ok nhưng muốn được học chuyên sâu, khó hơn, ra thành quả hơn, các kiến thức này hơi cơ bản xem 1 lần là nhớ và áp dụng được

Sheet Quà Q3
A1: Thủ khoa | B1: minhtri.hoang@garena.vn | C1: 61.5
A3: Row Labels | B3: Sum of Sum of Learning Hours | C3: Column 1 | D3: Quà Learning | E3: Quà Trainer | F3: Column 2 | G3: Hour | H3: Rank | I3: Quà
A4: minhkhoi.nguyen@garena.vn | B4: 75.5 | C4: Gà chăm Cao thủ | F4: {=IFERROR(INDEX(Sheet14!$B$1:$B967,MATCH(A4,Sheet14!$A$1:$A967,0)),"")} -> Gà chăm Cao thủ | G4: 2 | H4: Gà hơi chăm
A5: anhphuong.le@garena.vn | E5: Đế lót ly in hình Gà Learning | F5: {=IFERROR(INDEX(Sheet14!$B$1:$B967,MATCH(A5,Sheet14!$A$1:$A967,0)),"")}
A6: anhtu.nguyen@garena.vn | E6: Đế lót ly in hình Gà Learning | F6: {=IFERROR(INDEX(Sheet14!$B$1:$B967,MATCH(A6,Sheet14!$A$1:$A967,0)),"")}
A7: baoquoc.tongphuoc@garena.vn | E7: Đế lót ly in hình Gà Learning | F7: {=IFERROR(INDEX(Sheet14!$B$1:$B967,MATCH(A7,Sheet14!$A$1:$A967,0)),"")}
A8: quochung.khong@garena.vn | E8: Standee hình Gà | F8: {=IFERROR(INDEX(Sheet14!$B$1:$B967,MATCH(A8,Sheet14!$A$1:$A967,0)),"")} -> Gà chăm Kim cương
F9: {=IFERROR(INDEX(Sheet14!$B$1:$B967,MATCH(A9,Sheet14!$A$1:$A967,0)),"")}
F10: {=IFERROR(INDEX(Sheet14!$B$1:$B967,MATCH(A10,Sheet14!$A$1:$A967,0)),"")}
A11: minhtri.hoang@garena.vn | B11: 75 | C11: Gà chăm Cao thủ | D11: Standee hình Gà, Cốc in hình Gà | E11: Bình giữ nhiệt in hình Gà Learning | F11: {=IFERROR(INDEX(Sheet14!$B$1:$B967,MATCH(A11,Sheet14!$A$1:$A967,0)),"")} -> Gà chăm Kim cương | G11: 5 | H11: Gà chăm Tân thủ | I11: Pin kim loại
A12: hongduc.dao@garena.vn | B12: 72 | C12: Gà chăm Cao thủ | F12: Q1 | G12: 10 | H12: Gà chăm Kim cương | I12: Đế lót ly in hình Gà Learning,
A13: phuongthao.le@garena.vn | B13: 62.5 | C13: Gà chăm Cao thủ | D13: Cốc in hình Gà | F13: {=IFERROR(INDEX(Sheet14!$B$1:$B967,MATCH(A13,Sheet14!$A$1:$A967,0)),"")} | G13: 25 | H13: Gà chăm Tinh Anh | I13: Standee hình Gà,
A14: mylinh.pham@garena.vn | B14: 59.5 | C14: Gà chăm Cao thủ | D14: Pin kim loại, Đế lót ly in hình Gà Learning, Standee hình Gà, Cốc in hình Gà | F14: {=IFERROR(INDEX(Sheet14!$B$1:$B967,MATCH(A14,Sheet14!$A$1:$A967,0)),"")} | G14: 50 | H14: Gà chăm Cao thủ | I14: Cốc in hình Gà,
A15: viethop.nguyen@garena.vn | B15: 46 | C15: Gà chăm Tinh Anh | F15: {=IFERROR(INDEX(Sheet14!$B$1:$B967,MATCH(A15,Sheet14!$A$1:$A967,0)),"")} -> Gà chăm Tinh Anh | G15: =IF(F15=C15,"","Tặng")
A16: lenam.to@garena.vn | B16: 41.5 | C16: Gà chăm Tinh Anh | D16: Standee hình Gà | F16: {=IFERROR(INDEX(Sheet14!$B$1:$B967,MATCH(A16,Sheet14!$A$1:$A967,0)),"")} -> Gà chăm Kim cương | G16: =IF(F16=C16,"","Tặng") -> Tặng
A17: quanghuy.duong@garena.vn | B17: 41 | C17: Gà chăm Tinh Anh | D17: Đế lót ly in hình Gà Learning, Standee hình Gà | F17: {=IFERROR(INDEX(Sheet14!$B$1:$B967,MATCH(A17,Sheet14!$A$1:$A967,0)),"")} -> Gà chăm Tân thủ | G17: =IF(F17=C17,"","Tặng") -> Tặng
A18: tiendat.nguyen@garena.vn | B18: 39.5 | C18: Gà chăm Tinh Anh | D18: Pin kim loại, Đế lót ly in hình Gà Learning, Standee hình Gà | F18: {=IFERROR(INDEX(Sheet14!$B$1:$B967,MATCH(A18,Sheet14!$A$1:$A967,0)),"")} | G18: =IF(F18=C18,"","Tặng") -> Tặng
A19: anhtuan.mai@garena.vn | B19: 39.5 | C19: Gà chăm Tinh Anh | D19: Pin kim loại, Đế lót ly in hình Gà Learning, Standee hình Gà | F19: {=IFERROR(INDEX(Sheet14!$B$1:$B967,MATCH(A19,Sheet14!$A$1:$A967,0)),"")} | G19: =IF(F19=C19,"","Tặng") -> Tặng
A20: traanh.au@garena.vn | B20: 39.5 | C20: Gà chăm Tinh Anh | D20: Standee hình Gà | F20: {=IFERROR(INDEX(Sheet14!$B$1:$B967,MATCH(A20,Sheet14!$A$1:$A967,0)),"")} -> Gà chăm Kim cương | G20: =IF(F20=C20,"","Tặng") -> Tặng
A21: thienkhoa.le@garena.vn | B21: 39 | C21: Gà chăm Tinh Anh | D21: Pin kim loại, Đế lót ly in hình Gà Learning, Standee hình Gà | E21: Cốc in hình Gà | F21: {=IFERROR(INDEX(Sheet14!$B$1:$B967,MATCH(A21,Sheet14!$A$1:$A967,0)),"")} | G21: =IF(F21=C21,"","Tặng") -> Tặng
A22: anhvu.huynh@garena.vn | B22: 35.5 | C22: Gà chăm Tinh Anh | D22: Pin kim loại, Đế lót ly in hình Gà Learning, Standee hình Gà | F22: {=IFERROR(INDEX(Sheet14!$B$1:$B967,MATCH(A22,Sheet14!$A$1:$A967,0)),"")} | G22: =IF(F22=C22,"","Tặng") -> Tặng
A23: duytuan.nguyen@garena.vn | B23: 33.5 | C23: Gà chăm Tinh Anh | D23: Đế lót ly in hình Gà Learning, Standee hình Gà | E23: Pin kim loại, Cốc in hình Gà | F23: {=IFERROR(INDEX(Sheet14!$B$1:$B967,MATCH(A23,Sheet14!$A$1:$A967,0)),"")} -> Gà chăm Tân thủ | G23: =IF(F23=C23,"","Tặng") -> Tặng
A24: vietanh.than@garena.vn | B24: 33.5 | C24: Gà chăm Tinh Anh | D24: Đế lót ly in hình Gà Learning, Standee hình Gà | F24: {=IFERROR(INDEX(Sheet14!$B$1:$B967,MATCH(A24,Sheet14!$A$1:$A967,0)),"")} -> Gà chăm Tân thủ | G24: =IF(F24=C24,"","Tặng") -> Tặng
A25: thuanh.hotran@garena.vn | B25: 33.5 | C25: Gà chăm Tinh Anh | D25: Standee hình Gà | F25: {=IFERROR(INDEX(Sheet14!$B$1:$B967,MATCH(A25,Sheet14!$A$1:$A967,0)),"")} -> Gà chăm Kim cương | G25: =IF(F25=C25,"","Tặng") -> Tặng
A26: thieuky.tran@garena.vn | B26: 33.5 | C26: Gà chăm Tinh Anh | D26: Pin kim loại, Đế lót ly in hình Gà Learning, Standee hình Gà | F26: {=IFERROR(INDEX(Sheet14!$B$1:$B967,MATCH(A26,Sheet14!$A$1:$A967,0)),"")} | G26: =IF(F26=C26,"","Tặng") -> Tặng
A27: thucanh.nguyentran@garena.vn | B27: 33.5 | C27: Gà chăm Tinh Anh | D27: Pin kim loại, Đế lót ly in hình Gà Learning, Standee hình Gà | F27: {=IFERROR(INDEX(Sheet14!$B$1:$B967,MATCH(A27,Sheet14!$A$1:$A967,0)),"")} | G27: =IF(F27=C27,"","Tặng") -> Tặng
A28: ngoctoan.nguyen@garena.vn | B28: 33.5 | C28: Gà chăm Tinh Anh | D28: Pin kim loại, Đế lót ly in hình Gà Learning, Standee hình Gà | F28: {=IFERROR(INDEX(Sheet14!$B$1:$B967,MATCH(A28,Sheet14!$A$1:$A967,0)),"")} | G28: =IF(F28=C28,"","Tặng") -> Tặng
A29: vietanh.pham@garena.vn | B29: 33 | C29: Gà chăm Tinh Anh | D29: Pin kim loại, Đế lót ly in hình Gà Learning, Standee hình Gà | F29: {=IFERROR(INDEX(Sheet14!$B$1:$B967,MATCH(A29,Sheet14!$A$1:$A967,0)),"")} | G29: =IF(F29=C29,"","Tặng") -> Tặng
A30: huyenanh.phan@garena.vn | B30: 31 | C30: Gà chăm Tinh Anh | D30: Standee hình Gà | E30: Cốc in hình Gà, Đế lót ly in hình Gà Learning | F30: {=IFERROR(INDEX(Sheet14!$B$1:$B967,MATCH(A30,Sheet14!$A$1:$A967,0)),"")} -> Gà chăm Kim cương | G30: =IF(F30=C30,"","Tặng") -> Tặng
A31: quochuy.dinh@garena.vn | B31: 30 | C31: Gà chăm Tinh Anh | D31: Pin kim loại, Đế lót ly in hình Gà Learning, Standee hình Gà | F31: {=IFERROR(INDEX(Sheet14!$B$1:$B967,MATCH(A31,Sheet14!$A$1:$A967,0)),"")} | G31: =IF(F31=C31,"","Tặng") -> Tặng
A32: myhanh.luu@garena.vn | B32: 30 | C32: Gà chăm Tinh Anh | D32: Pin kim loại, Đế lót ly in hình Gà Learning, Standee hình Gà | F32: {=IFERROR(INDEX(Sheet14!$B$1:$B967,MATCH(A32,Sheet14!$A$1:$A967,0)),"")} | G32: =IF(F32=C32,"","Tặng") -> Tặng
A33: quangduc.tran@garena.vn | B33: 29.5 | C33: Gà chăm Tinh Anh | D33: Pin kim loại, Đế lót ly in hình Gà Learning, Standee hình Gà | F33: {=IFERROR(INDEX(Sheet14!$B$1:$B967,MATCH(A33,Sheet14!$A$1:$A967,0)),"")} | G33: =IF(F33=C33,"","Tặng") -> Tặng
A34: trang.nguyen@garena.vn | B34: 29.5 | C34: Gà chăm Tinh Anh | D34: Standee hình Gà | F34: {=IFERROR(INDEX(Sheet14!$B$1:$B967,MATCH(A34,Sheet14!$A$1:$A967,0)),"")} -> Gà chăm Kim cương | G34: =IF(F34=C34,"","Tặng") -> Tặng
A35: quangtuan.dao@garena.vn | B35: 29.5 | C35: Gà chăm Tinh Anh | D35: Pin kim loại, Đế lót ly in hình Gà Learning, Standee hình Gà | F35: {=IFERROR(INDEX(Sheet14!$B$1:$B967,MATCH(A35,Sheet14!$A$1:$A967,0)),"")} | G35: =IF(F35=C35,"","Tặng") -> Tặng
A36: theviet.nguyen@garena.vn | B36: 28 | C36: Gà chăm Tinh Anh | D36: Pin kim loại, Đế lót ly in hình Gà Learning, Standee hình Gà | F36: {=IFERROR(INDEX(Sheet14!$B$1:$B967,MATCH(A36,Sheet14!$A$1:$A967,0)),"")} | G36: =IF(F36=C36,"","Tặng") -> Tặng
A37: sygiap.nguyen@garena.vn | B37: 28 | C37: Gà chăm Tinh Anh | D37: Pin kim loại, Đế lót ly in hình Gà Learning, Standee hình Gà | F37: {=IFERROR(INDEX(Sheet14!$B$1:$B967,MATCH(A37,Sheet14!$A$1:$A967,0)),"")} | G37: =IF(F37=C37,"","Tặng") -> Tặng
A38: banhat.nguyen@garena.vn | B38: 27 | C38: Gà chăm Tinh Anh | D38: Pin kim loại, Đế lót ly in hình Gà Learning, Standee hình Gà | E38: Cốc in hình Gà | F38: {=IFERROR(INDEX(Sheet14!$B$1:$B967,MATCH(A38,Sheet14!$A$1:$A967,0)),"")} | G38: =IF(F38=C38,"","Tặng") -> Tặng
A39: minhkhoi.tran@garena.vn | B39: 27 | C39: Gà chăm Tinh Anh | D39: Pin kim loại, Đế lót ly in hình Gà Learning, Standee hình Gà | F39: {=IFERROR(INDEX(Sheet14!$B$1:$B967,MATCH(A39,Sheet14!$A$1:$A967,0)),"")} | G39: =IF(F39=C39,"","Tặng") -> Tặng
A40: huongly.dang@garena.vn | B40: 25.5 | C40: Gà chăm Tinh Anh | D40: Pin kim loại, Đế lót ly in hình Gà Learning, Standee hình Gà | F40: {=IFERROR(INDEX(Sheet14!$B$1:$B967,MATCH(A40,Sheet14!$A$1:$A967,0)),"")} -> Gà chăm Kim cương | G40: =IF(F40=C40,"","Tặng") -> Tặng
A41: anhvu.an@garena.vn | B41: 24.5 | C41: Gà chăm Kim cương | D41: Pin kim loại, Đế lót ly in hình Gà Learning | F41: {=IFERROR(INDEX(Sheet14!$B$1:$B967,MATCH(A41,Sheet14!$A$1:$A967,0)),"")} | G41: =IF(F41=C41,"","Tặng") -> Tặng
A42: quocviet.vuong@garena.vn | B42: 24 | C42: Gà chăm Kim cương | D42: Pin kim loại, Đế lót ly in hình Gà Learning | E42: Standee hình Gà | F42: {=IFERROR(INDEX(Sheet14!$B$1:$B967,MATCH(A42,Sheet14!$A$1:$A967,0)),"")} | G42: =IF(F42=C42,"","Tặng") -> Tặng
A43: thanhtung.luu@garena.vn | B43: 24 | C43: Gà chăm Kim cương | D43: Pin kim loại, Đế lót ly in hình Gà Learning | F43: {=IFERROR(INDEX(Sheet14!$B$1:$B967,MATCH(A43,Sheet14!$A$1:$A967,0)),"")} | G43: =IF(F43=C43,"","Tặng") -> Tặng
A44: thutrang.pham@garena.vn | B44: 24 | C44: Gà chăm Kim cương | D44: Pin kim loại, Đế lót ly in hình Gà Learning | F44: {=IFERROR(INDEX(Sheet14!$B$1:$B967,MATCH(A44,Sheet14!$A$1:$A967,0)),"")} | G44: =IF(F44=C44,"","Tặng") -> Tặng
A45: phuongthao.dao@garena.vn | B45: 23.5 | C45: Gà chăm Kim cương | F45: {=IFERROR(INDEX(Sheet14!$B$1:$B967,MATCH(A45,Sheet14!$A$1:$A967,0)),"")} -> Gà chăm Kim cương | G45: =IF(F45=C45,"","Tặng")
A46: khaitrien.vuu@garena.vn | B46: 23.5 | C46: Gà chăm Kim cương | D46: Pin kim loại, Đế lót ly in hình Gà Learning | F46: {=IFERROR(INDEX(Sheet14!$B$1:$B967,MATCH(A46,Sheet14!$A$1:$A967,0)),"")} | G46: =IF(F46=C46,"","Tặng") -> Tặng
A47: mytram.nguyen@garena.vn | B47: 23.5 | C47: Gà chăm Kim cương | D47: Pin kim loại, Đế lót ly in hình Gà Learning | F47: {=IFERROR(INDEX(Sheet14!$B$1:$B967,MATCH(A47,Sheet14!$A$1:$A967,0)),"")} | G47: =IF(F47=C47,"","Tặng") -> Tặng
A48: ducanh.le@garena.vn | B48: 23 | C48: Gà chăm Kim cương | F48: {=IFERROR(INDEX(Sheet14!$B$1:$B967,MATCH(A48,Sheet14!$A$1:$A967,0)),"")} -> Gà chăm Kim cương | G48: =IF(F48=C48,"","Tặng")
A49: anhkhoa.nguyen@garena.vn | B49: 22 | C49: Gà chăm Kim cương | D49: Pin kim loại, Đế lót ly in hình Gà Learning | E49: Standee hình Gà | F49: {=IFERROR(INDEX(Sheet14!$B$1:$B967,MATCH(A49,Sheet14!$A$1:$A967,0)),"")} | G49: =IF(F49=C49,"","Tặng") -> Tặng
A50: huonggiang.nguyen@garena.vn | B50: 22 | C50: Gà chăm Kim cương | D50: Pin kim loại, Đế lót ly in hình Gà Learning | F50: {=IFERROR(INDEX(Sheet14!$B$1:$B967,MATCH(A50,Sheet14!$A$1:$A967,0)),"")} | G50: =IF(F50=C50,"","Tặng") -> Tặng
A51: hoale.vuong@garena.vn | B51: 22 | C51: Gà chăm Kim cương | D51: Pin kim loại, Đế lót ly in hình Gà Learning | F51: {=IFERROR(INDEX(Sheet14!$B$1:$B967,MATCH(A51,Sheet14!$A$1:$A967,0)),"")} | G51: =IF(F51=C51,"","Tặng") -> Tặng
A52: theminh.tu@garena.vn | B52: 22 | C52: Gà chăm Kim cương | D52: Pin kim loại, Đế lót ly in hình Gà Learning | F52: {=IFERROR(INDEX(Sheet14!$B$1:$B967,MATCH(A52,Sheet14!$A$1:$A967,0)),"")} | G52: =IF(F52=C52,"","Tặng") -> Tặng
A53: theanh.nguyennhu@garena.vn | B53: 22 | C53: Gà chăm Kim cương | D53: Pin kim loại, Đế lót ly in hình Gà Learning | F53: {=IFERROR(INDEX(Sheet14!$B$1:$B967,MATCH(A53,Sheet14!$A$1:$A967,0)),"")} | G53: =IF(F53=C53,"","Tặng") -> Tặng
A54: honghanh.nguyen@garena.vn | B54: 21.5 | C54: Gà chăm Kim cương | D54: Đế lót ly in hình Gà Learning | F54: {=IFERROR(INDEX(Sheet14!$B$1:$B967,MATCH(A54,Sheet14!$A$1:$A967,0)),"")} -> Gà chăm Tân thủ | G54: =IF(F54=C54,"","Tặng") -> Tặng
A55: phuocquang.nhan@garena.vn | B55: 21 | C55: Gà chăm Kim cương | D55: Pin kim loại, Đế lót ly in hình Gà Learning | F55: {=IFERROR(INDEX(Sheet14!$B$1:$B967,MATCH(A55,Sheet14!$A$1:$A967,0)),"")} | G55: =IF(F55=C55,"","Tặng") -> Tặng
A56: thainam.luong@garena.vn | B56: 20 | C56: Gà chăm Kim cương | D56: Pin kim loại, Đế lót ly in hình Gà Learning | F56: {=IFERROR(INDEX(Sheet14!$B$1:$B967,MATCH(A56,Sheet14!$A$1:$A967,0)),"")} | G56: =IF(F56=C56,"","Tặng") -> Tặng
A57: caocuong.tran@garena.vn | B57: 20 | C57: Gà chăm Kim cương | D57: Pin kim loại, Đế lót ly in hình Gà Learning | F57: {=IFERROR(INDEX(Sheet14!$B$1:$B967,MATCH(A57,Sheet14!$A$1:$A967,0)),"")} | G57: =IF(F57=C57,"","Tặng") -> Tặng
A58: tienthanh.tran@garena.vn | B58: 20 | C58: Gà chăm Kim cương | D58: Pin kim loại, Đế lót ly in hình Gà Learning | E58: Cốc in hình Gà | F58: {=IFERROR(INDEX(Sheet14!$B$1:$B967,MATCH(A58,Sheet14!$A$1:$A967,0)),"")} | G58: =IF(F58=C58,"","Tặng") -> Tặng
A59: maithanh.le@garena.vn | B59: 20 | C59: Gà chăm Kim cương | D59: Pin kim loại, Đế lót ly in hình Gà Learning | F59: {=IFERROR(INDEX(Sheet14!$B$1:$B967,MATCH(A59,Sheet14!$A$1:$A967,0)),"")} | G59: =IF(F59=C59,"","Tặng") -> Tặng
A60: hainguyen.dao@garena.vn | B60: 20 | C60: Gà chăm Kim cương | D60: Pin kim loại, Đế lót ly in hình Gà Learning | F60: {=IFERROR(INDEX(Sheet14!$B$1:$B967,MATCH(A60,Sheet14!$A$1:$A967,0)),"")} | G60: =IF(F60=C60,"","Tặng") -> Tặng
A61: maiphuong.pham@garena.vn | B61: 19.5 | C61: Gà chăm Kim cương | F61: {=IFERROR(INDEX(Sheet14!$B$1:$B967,MATCH(A61,Sheet14!$A$1:$A967,0)),"")} -> Gà chăm Kim cương | G61: =IF(F61=C61,"","Tặng")
A62: huuvuong.nguyen@garena.vn | B62: 19.5 | C62: Gà chăm Kim cương | D62: Đế lót ly in hình Gà Learning | E62: Standee hình Gà | F62: {=IFERROR(INDEX(Sheet14!$B$1:$B967,MATCH(A62,Sheet14!$A$1:$A967,0)),"")} -> Gà chăm Tân thủ | G62: =IF(F62=C62,"","Tặng") -> Tặng
A63: quangvinh.tran@garena.vn | B63: 19.5 | C63: Gà chăm Kim cương | D63: Đế lót ly in hình Gà Learning | F63: {=IFERROR(INDEX(Sheet14!$B$1:$B967,MATCH(A63,Sheet14!$A$1:$A967,0)),"")} -> Gà chăm Tân thủ | G63: =IF(F63=C63,"","Tặng") -> Tặng
A64: ducthao.tran@garena.vn | B64: 19 | C64: Gà chăm Kim cương | F64: {=IFERROR(INDEX(Sheet14!$B$1:$B967,MATCH(A64,Sheet14!$A$1:$A967,0)),"")} -> Gà chăm Kim cương | G64: =IF(F64=C64,"","Tặng")
A65: ducnam.hoang@garena.vn | B65: 18 | C65: Gà chăm Kim cương | D65: Pin kim loại, Đế lót ly in hình Gà Learning | F65: {=IFERROR(INDEX(Sheet14!$B$1:$B967,MATCH(A65,Sheet14!$A$1:$A967,0)),"")} | G65: =IF(F65=C65,"","Tặng") -> Tặng
A66: anhchau.tran@garena.vn | B66: 18 | C66: Gà chăm Kim cương | D66: Pin kim loại, Đế lót ly in hình Gà Learning | F66: {=IFERROR(INDEX(Sheet14!$B$1:$B967,MATCH(A66,Sheet14!$A$1:$A967,0)),"")} | G66: =IF(F66=C66,"","Tặng") -> Tặng
A67: quochung.tran@garena.vn | B67: 18 | C67: Gà chăm Kim cương | D67: Pin kim loại, Đế lót ly in hình Gà Learning | F67: {=IFERROR(INDEX(Sheet14!$B$1:$B967,MATCH(A67,Sheet14!$A$1:$A967,0)),"")} | G67: =IF(F67=C67,"","Tặng") -> Tặng
A68: hoanganh.cao@garena.vn | B68: 18 | C68: Gà chăm Kim cương | D68: Pin kim loại, Đế lót ly in hình Gà Learning | F68: {=IFERROR(INDEX(Sheet14!$B$1:$B967,MATCH(A68,Sheet14!$A$1:$A967,0)),"")} | G68: =IF(F68=C68,"","Tặng") -> Tặng
A69: quoctuan.tran@garena.vn | B69: 17.5 | C69: Gà chăm Kim cương | F69: {=IFERROR(INDEX(Sheet14!$B$1:$B967,MATCH(A69,Sheet14!$A$1:$A967,0)),"")} -> Gà chăm Kim cương | G69: =IF(F69=C69,"","Tặng")
A70: khaikien.duong@garena.vn | B70: 17.5 | C70: Gà chăm Kim cương | F70: {=IFERROR(INDEX(Sheet14!$B$1:$B967,MATCH(A70,Sheet14!$A$1:$A967,0)),"")} -> Gà chăm Kim cương | G70: =IF(F70=C70,"","Tặng")
A71: phuongthao.hoang@garena.vn | B71: 17.5 | C71: Gà chăm Kim cương | F71: {=IFERROR(INDEX(Sheet14!$B$1:$B967,MATCH(A71,Sheet14!$A$1:$A967,0)),"")} -> Gà chăm Kim cương | G71: =IF(F71=C71,"","Tặng")
A72: khanhhoang.tran@garena.vn | B72: 17.5 | C72: Gà chăm Kim cương | F72: {=IFERROR(INDEX(Sheet14!$B$1:$B967,MATCH(A72,Sheet14!$A$1:$A967,0)),"")} -> Gà chăm Tân thủ | G72: =IF(F72=C72,"","Tặng") -> Tặng
A73: phuonglinh.pham@garena.vn | B73: 17.5 | C73: Gà chăm Kim cương | D73: Pin kim loại, Đế lót ly in hình Gà Learning | F73: {=IFERROR(INDEX(Sheet14!$B$1:$B967,MATCH(A73,Sheet14!$A$1:$A967,0)),"")} | G73: =IF(F73=C73,"","Tặng") -> Tặng
A74: chithanh.nguyen@garena.vn | B74: 17.5 | C74: Gà chăm Kim cương | D74: Pin kim loại, Đế lót ly in hình Gà Learning | E74: Standee hình Gà | F74: {=IFERROR(INDEX(Sheet14!$B$1:$B967,MATCH(A74,Sheet14!$A$1:$A967,0)),"")} | G74: =IF(F74=C74,"","Tặng") -> Tặng
A75: ngoctram.nguyen@garena.vn | B75: 16 | C75: Gà chăm Kim cương | D75: Pin kim loại, Đế lót ly in hình Gà Learning | F75: {=IFERROR(INDEX(Sheet14!$B$1:$B967,MATCH(A75,Sheet14!$A$1:$A967,0)),"")} | G75: =IF(F75=C75,"","Tặng") -> Tặng
A76: thaianh.tran@garena.vn | B76: 15.5 | C76: Gà chăm Kim cương | D76: Pin kim loại, Đế lót ly in hình Gà Learning | F76: {=IFERROR(INDEX(Sheet14!$B$1:$B967,MATCH(A76,Sheet14!$A$1:$A967,0)),"")} | G76: =IF(F76=C76,"","Tặng") -> Tặng
A77: chicong.vu@garena.vn | B77: 15.5 | C77: Gà chăm Kim cương | F77: {=IFERROR(INDEX(Sheet14!$B$1:$B967,MATCH(A77,Sheet14!$A$1:$A967,0)),"")} -> Gà chăm Kim cương | G77: =IF(F77=C77,"","Tặng")
A78: lanchi.vu@garena.vn | B78: 15.5 | C78: Gà chăm Kim cương | F78: {=IFERROR(INDEX(Sheet14!$B$1:$B967,MATCH(A78,Sheet14!$A$1:$A967,0)),"")} -> Gà chăm Kim cương | G78: =IF(F78=C78,"","Tặng")
A79: thanhtuan.nguyen@garena.vn | B79: 15.5 | C79: Gà chăm Kim cương | D79: Pin kim loại, Đế lót ly in hình Gà Learning | F79: {=IFERROR(INDEX(Sheet14!$B$1:$B967,MATCH(A79,Sheet14!$A$1:$A967,0)),"")} | G79: =IF(F79=C79,"","Tặng") -> Tặng
A80: huuthinh.nguyen@garena.vn | B80: 15.5 | C80: Gà chăm Kim cương | D80: Pin kim loại, Đế lót ly in hình Gà Learning | E80: Standee hình Gà | F80: {=IFERROR(INDEX(Sheet14!$B$1:$B967,MATCH(A80,Sheet14!$A$1:$A967,0)),"")} | G80: =IF(F80=C80,"","Tặng") -> Tặng
A81: thutrang.tran@garena.vn | B81: 14 | C81: Gà chăm Kim cương | F81: {=IFERROR(INDEX(Sheet14!$B$1:$B967,MATCH(A81,Sheet14!$A$1:$A967,0)),"")} -> Gà chăm Kim cương | G81: =IF(F81=C81,"","Tặng")
A82: thaiha.pham@garena.vn | B82: 14 | C82: Gà chăm Kim cương | D82: Pin kim loại, Đế lót ly in hình Gà Learning | F82: {=IFERROR(INDEX(Sheet14!$B$1:$B967,MATCH(A82,Sheet14!$A$1:$A967,0)),"")} | G82: =IF(F82=C82,"","Tặng") -> Tặng
A83: quanghuy.truong@garena.vn | B83: 13.5 | C83: Gà chăm Kim cương | F83: {=IFERROR(INDEX(Sheet14!$B$1:$B967,MATCH(A83,Sheet14!$A$1:$A967,0)),"")} -> Gà chăm Kim cương | G83: =IF(F83=C83,"","Tặng")
A84: quanghoat.nguyen@garena.vn | B84: 13.5 | C84: Gà chăm Kim cương | F84: {=IFERROR(INDEX(Sheet14!$B$1:$B967,MATCH(A84,Sheet14!$A$1:$A967,0)),"")} -> Gà chăm Kim cương | G84: =IF(F84=C84,"","Tặng")
A85: vanhiep.mai@garena.vn | B85: 13.5 | C85: Gà chăm Kim cương | D85: Pin kim loại, Đế lót ly in hình Gà Learning | F85: {=IFERROR(INDEX(Sheet14!$B$1:$B967,MATCH(A85,Sheet14!$A$1:$A967,0)),"")} | G85: =IF(F85=C85,"","Tặng") -> Tặng
A86: haison.tran@garena.vn | B86: 13.5 | C86: Gà chăm Kim cương | F86: {=IFERROR(INDEX(Sheet14!$B$1:$B967,MATCH(A86,Sheet14!$A$1:$A967,0)),"")} -> Gà chăm Kim cương | G86: =IF(F86=C86,"","Tặng")
A87: minhtri.le@garena.vn | B87: 13.5 | C87: Gà chăm Kim cương | D87: Pin kim loại, Đế lót ly in hình Gà Learning | F87: {=IFERROR(INDEX(Sheet14!$B$1:$B967,MATCH(A87,Sheet14!$A$1:$A967,0)),"")} | G87: =IF(F87=C87,"","Tặng") -> Tặng
A88: quochung.khong@garena.vn | B88: 13.5 | C88: Gà chăm Kim cương | F88: {=IFERROR(INDEX(Sheet14!$B$1:$B967,MATCH(A88,Sheet14!$A$1:$A967,0)),"")} -> Gà chăm Kim cương | G88: =IF(F88=C88,"","Tặng")
A89: anhkhoa.le@garena.vn | B89: 13.5 | C89: Gà chăm Kim cương | D89: Pin kim loại, Đế lót ly in hình Gà Learning | F89: {=IFERROR(INDEX(Sheet14!$B$1:$B967,MATCH(A89,Sheet14!$A$1:$A967,0)),"")} | G89: =IF(F89=C89,"","Tặng") -> Tặng
A90: thutrang.nguyenthi@garena.vn | B90: 12 | C90: Gà chăm Kim cương | F90: {=IFERROR(INDEX(Sheet14!$B$1:$B967,MATCH(A90,Sheet14!$A$1:$A967,0)),"")} -> Gà chăm Kim cương | G90: =IF(F90=C90,"","Tặng")
A91: thutrang.nguyen@garena.vn | B91: 12 | C91: Gà chăm Kim cương | F91: {=IFERROR(INDEX(Sheet14!$B$1:$B967,MATCH(A91,Sheet14!$A$1:$A967,0)),"")} -> Gà chăm Kim cương | G91: =IF(F91=C91,"","Tặng")
A92: phuonglien.ngo@garena.vn | B92: 12 | C92: Gà chăm Kim cương | F92: {=IFERROR(INDEX(Sheet14!$B$1:$B967,MATCH(A92,Sheet14!$A$1:$A967,0)),"")} -> Gà chăm Kim cương | G92: =IF(F92=C92,"","Tặng")
A93: thithanh.le@garena.vn | B93: 12 | C93: Gà chăm Kim cương | F93: {=IFERROR(INDEX(Sheet14!$B$1:$B967,MATCH(A93,Sheet14!$A$1:$A967,0)),"")} -> Gà chăm Kim cương | G93: =IF(F93=C93,"","Tặng")
A94: vananh@garena.vn | B94: 12 | C94: Gà chăm Kim cương | F94: {=IFERROR(INDEX(Sheet14!$B$1:$B967,MATCH(A94,Sheet14!$A$1:$A967,0)),"")} -> Gà chăm Kim cương | G94: =IF(F94=C94,"","Tặng")
A95: vinhyen.dao@garena.vn | B95: 11.5 | C95: Gà chăm Kim cương | F95: {=IFERROR(INDEX(Sheet14!$B$1:$B967,MATCH(A95,Sheet14!$A$1:$A967,0)),"")} -> Gà chăm Kim cương | G95: =IF(F95=C95,"","Tặng")
A96: hongduc.le@garena.vn | B96: 11.5 | C96: Gà chăm Kim cương | F96: {=IFERROR(INDEX(Sheet14!$B$1:$B967,MATCH(A96,Sheet14!$A$1:$A967,0)),"")} -> Gà chăm Kim cương | G96: =IF(F96=C96,"","Tặng")
A97: thanhhao.pham@garena.vn | B97: 11.5 | C97: Gà chăm Kim cương | F97: {=IFERROR(INDEX(Sheet14!$B$1:$B967,MATCH(A97,Sheet14!$A$1:$A967,0)),"")} -> Gà chăm Kim cương | G97: =IF(F97=C97,"","Tặng")
A98: thuyquynh.luong@garena.vn | B98: 11 | C98: Gà chăm Kim cương | D98: Đế lót ly in hình Gà Learning | F98: {=IFERROR(INDEX(Sheet14!$B$1:$B967,MATCH(A98,Sheet14!$A$1:$A967,0)),"")} -> Gà chăm Tân thủ | G98: =IF(F98=C98,"","Tặng") -> Tặng
A99: ngocminh.le@garena.vn | B99: 9.5 | C99: Gà chăm Tân thủ | D99: Pin kim loại | F99: {=IFERROR(INDEX(Sheet14!$B$1:$B967,MATCH(A99,Sheet14!$A$1:$A967,0)),"")} | G99: =IF(F99=C99,"","Tặng") -> Tặng
A100: thuba.dinh@garena.vn | B100: 9.5 | C100: Gà chăm Tân thủ | F100: {=IFERROR(INDEX(Sheet14!$B$1:$B967,MATCH(A100,Sheet14!$A$1:$A967,0)),"")} -> Gà chăm Tân thủ | G100: =IF(F100=C100,"","Tặng")
A101: ngoclong.nguyen@garena.vn | B101: 9.5 | C101: Gà chăm Tân thủ | F101: {=IFERROR(INDEX(Sheet14!$B$1:$B967,MATCH(A101,Sheet14!$A$1:$A967,0)),"")} -> Gà chăm Tân thủ | G101: =IF(F101=C101,"","Tặng")
...

Sheet Copy of Quà Q3
A1: Thủ khoa | B1: 61.5
A3: Mail | B3: Huy hiệu | C3: Quà tặng 2025 | D3: Quà trainer | E3: Ký nhận | F3: Địa điểm
A4: anhphuong.le@garena.vn | D4: Đế lót ly in hình Gà Learning | F4: Hanoi
A5: anhtu.nguyen@garena.vn | D5: Đế lót ly in hình Gà Learning | F5: Hanoi
A6: baoquoc.tongphuoc@garena.vn | D6: Đế lót ly in hình Gà Learning | F6: Ho Chi Minh
A7: quochung.khong@garena.vn | D7: Standee hình Gà | F7: Hanoi
A8: minhtri.hoang@garena.vn | B8: Gà chăm Cao thủ | C8: Standee hình Gà, Cốc in hình Gà | D8: Bình giữ nhiệt in hình Gà Learning | F8: Hanoi
A9: phuongthao.le@garena.vn | B9: Gà chăm Cao thủ | C9: Cốc in hình Gà | F9: Ho Chi Minh
A10: mylinh.pham@garena.vn | B10: Gà chăm Cao thủ | C10: Pin kim loại, Đế lót ly in hình Gà Learning, Standee hình Gà, Cốc in hình Gà | F10: Hanoi
A11: lenam.to@garena.vn | B11: Gà chăm Tinh Anh | C11: Standee hình Gà | F11: Hanoi
A12: quanghuy.duong@garena.vn | B12: Gà chăm Tinh Anh | C12: Đế lót ly in hình Gà Learning, Standee hình Gà | F12: Hanoi
A13: tiendat.nguyen@garena.vn | B13: Gà chăm Tinh Anh | C13: Pin kim loại, Đế lót ly in hình Gà Learning, Standee hình Gà | F13: Ho Chi Minh
A14: anhtuan.mai@garena.vn | B14: Gà chăm Tinh Anh | C14: Pin kim loại, Đế lót ly in hình Gà Learning, Standee hình Gà | F14: Hanoi
A15: traanh.au@garena.vn | B15: Gà chăm Tinh Anh | C15: Standee hình Gà | F15: Hanoi
A16: thienkhoa.le@garena.vn | B16: Gà chăm Tinh Anh | C16: Pin kim loại, Đế lót ly in hình Gà Learning, Standee hình Gà | D16: Cốc in hình Gà | F16: Ho Chi Minh
A17: anhvu.huynh@garena.vn | B17: Gà chăm Tinh Anh | C17: Pin kim loại, Đế lót ly in hình Gà Learning, Standee hình Gà | F17: Ho Chi Minh
A18: duytuan.nguyen@garena.vn | B18: Gà chăm Tinh Anh | C18: Đế lót ly in hình Gà Learning, Standee hình Gà | D18: Pin kim loại, Cốc in hình Gà | F18: Hanoi
A19: vietanh.than@garena.vn | B19: Gà chăm Tinh Anh | C19: Đế lót ly in hình Gà Learning, Standee hình Gà | F19: Hanoi
A20: thuanh.hotran@garena.vn | B20: Gà chăm Tinh Anh | C20: Standee hình Gà | F20: Hanoi
A21: thieuky.tran@garena.vn | B21: Gà chăm Tinh Anh | C21: Pin kim loại, Đế lót ly in hình Gà Learning, Standee hình Gà | F21: Ho Chi Minh
A22: thucanh.nguyentran@garena.vn | B22: Gà chăm Tinh Anh | C22: Pin kim loại, Đế lót ly in hình Gà Learning, Standee hình Gà | F22: Ho Chi Minh
A23: ngoctoan.nguyen@garena.vn | B23: Gà chăm Tinh Anh | C23: Pin kim loại, Đế lót ly in hình Gà Learning, Standee hình Gà | F23: Hanoi
A24: vietanh.pham@garena.vn | B24: Gà chăm Tinh Anh | C24: Pin kim loại, Đế lót ly in hình Gà Learning, Standee hình Gà | F24: Hanoi
A25: huyenanh.phan@garena.vn | B25: Gà chăm Tinh Anh | C25: Standee hình Gà | D25: Cốc in hình Gà, Đế lót ly in hình Gà Learning | F25: Hanoi
A26: quochuy.dinh@garena.vn | B26: Gà chăm Tinh Anh | C26: Pin kim loại, Đế lót ly in hình Gà Learning, Standee hình Gà | F26: Ho Chi Minh
A27: myhanh.luu@garena.vn | B27: Gà chăm Tinh Anh | C27: Pin kim loại, Đế lót ly in hình Gà Learning, Standee hình Gà | F27: Hanoi
A28: quangduc.tran@garena.vn | B28: Gà chăm Tinh Anh | C28: Pin kim loại, Đế lót ly in hình Gà Learning, Standee hình Gà | F28: Hanoi
A29: trang.nguyen@garena.vn | B29: Gà chăm Tinh Anh | C29: Standee hình Gà | F29: Hanoi
A30: quangtuan.dao@garena.vn | B30: Gà chăm Tinh Anh | C30: Pin kim loại, Đế lót ly in hình Gà Learning, Standee hình Gà | F30: Hanoi
A31: theviet.nguyen@garena.vn | B31: Gà chăm Tinh Anh | C31: Pin kim loại, Đế lót ly in hình Gà Learning, Standee hình Gà | F31: Ho Chi Minh
A32: sygiap.nguyen@garena.vn | B32: Gà chăm Tinh Anh | C32: Pin kim loại, Đế lót ly in hình Gà Learning, Standee hình Gà | F32: Ho Chi Minh
A33: banhat.nguyen@garena.vn | B33: Gà chăm Tinh Anh | C33: Pin kim loại, Đế lót ly in hình Gà Learning, Standee hình Gà | D33: Cốc in hình Gà | F33: Ho Chi Minh
A34: minhkhoi.tran@garena.vn | B34: Gà chăm Tinh Anh | C34: Pin kim loại, Đế lót ly in hình Gà Learning, Standee hình Gà | F34: Ho Chi Minh
A35: anhvu.an@garena.vn | B35: Gà chăm Kim cương | C35: Pin kim loại, Đế lót ly in hình Gà Learning | F35: Ho Chi Minh
A36: quocviet.vuong@garena.vn | B36: Gà chăm Kim cương | C36: Pin kim loại, Đế lót ly in hình Gà Learning | D36: Standee hình Gà | F36: Ho Chi Minh
A37: thanhtung.luu@garena.vn | B37: Gà chăm Kim cương | C37: Pin kim loại, Đế lót ly in hình Gà Learning | F37: Ho Chi Minh
A38: thutrang.pham@garena.vn | B38: Gà chăm Kim cương | C38: Pin kim loại, Đế lót ly in hình Gà Learning | F38: Hanoi
A39: khaitrien.vuu@garena.vn | B39: Gà chăm Kim cương | C39: Pin kim loại, Đế lót ly in hình Gà Learning | F39: Ho Chi Minh
A40: mytram.nguyen@garena.vn | B40: Gà chăm Kim cương | C40: Pin kim loại, Đế lót ly in hình Gà Learning | F40: Ho Chi Minh
A41: anhkhoa.nguyen@garena.vn | B41: Gà chăm Kim cương | C41: Pin kim loại, Đế lót ly in hình Gà Learning | D41: Standee hình Gà | F41: Ho Chi Minh
A42: huonggiang.nguyen@garena.vn | B42: Gà chăm Kim cương | C42: Pin kim loại, Đế lót ly in hình Gà Learning | F42: Ho Chi Minh
A43: hoale.vuong@garena.vn | B43: Gà chăm Kim cương | C43: Pin kim loại, Đế lót ly in hình Gà Learning | F43: Hanoi
A44: theminh.tu@garena.vn | B44: Gà chăm Kim cương | C44: Pin kim loại, Đế lót ly in hình Gà Learning | F44: Ho Chi Minh
A45: theanh.nguyennhu@garena.vn | B45: Gà chăm Kim cương | C45: Pin kim loại, Đế lót ly in hình Gà Learning | F45: Hanoi
A46: honghanh.nguyen@garena.vn | B46: Gà chăm Kim cương | C46: Đế lót ly in hình Gà Learning | F46: Hanoi
A47: phuocquang.nhan@garena.vn | B47: Gà chăm Kim cương | C47: Pin kim loại, Đế lót ly in hình Gà Learning | F47: Ho Chi Minh
A48: thainam.luong@garena.vn | B48: Gà chăm Kim cương | C48: Pin kim loại, Đế lót ly in hình Gà Learning | F48: Hanoi
A49: caocuong.tran@garena.vn | B49: Gà chăm Kim cương | C49: Pin kim loại, Đế lót ly in hình Gà Learning | F49: Hanoi
A50: tienthanh.tran@garena.vn | B50: Gà chăm Kim cương | C50: Pin kim loại, Đế lót ly in hình Gà Learning | D50: Cốc in hình Gà | F50: Hanoi
A51: maithanh.le@garena.vn | B51: Gà chăm Kim cương | C51: Pin kim loại, Đế lót ly in hình Gà Learning | F51: Hanoi
A52: hainguyen.dao@garena.vn | B52: Gà chăm Kim cương | C52: Pin kim loại, Đế lót ly in hình Gà Learning | F52: Hanoi
A53: huuvuong.nguyen@garena.vn | B53: Gà chăm Kim cương | C53: Đế lót ly in hình Gà Learning | D53: Standee hình Gà | F53: Hanoi
A54: quangvinh.tran@garena.vn | B54: Gà chăm Kim cương | C54: Đế lót ly in hình Gà Learning | F54: Hanoi
A55: ducnam.hoang@garena.vn | B55: Gà chăm Kim cương | C55: Pin kim loại, Đế lót ly in hình Gà Learning | F55: Hanoi
A56: anhchau.tran@garena.vn | B56: Gà chăm Kim cương | C56: Pin kim loại, Đế lót ly in hình Gà Learning | F56: Hanoi
A57: quochung.tran@garena.vn | B57: Gà chăm Kim cương | C57: Pin kim loại, Đế lót ly in hình Gà Learning | F57: Hanoi
A58: hoanganh.cao@garena.vn | B58: Gà chăm Kim cương | C58: Pin kim loại, Đế lót ly in hình Gà Learning | F58: Hanoi
A59: phuonglinh.pham@garena.vn | B59: Gà chăm Kim cương | C59: Pin kim loại, Đế lót ly in hình Gà Learning | F59: Ho Chi Minh
A60: chithanh.nguyen@garena.vn | B60: Gà chăm Kim cương | C60: Pin kim loại, Đế lót ly in hình Gà Learning | D60: Standee hình Gà | F60: Hanoi
A61: ngoctram.nguyen@garena.vn | B61: Gà chăm Kim cương | C61: Pin kim loại, Đế lót ly in hình Gà Learning | F61: Hanoi
A62: thaianh.tran@garena.vn | B62: Gà chăm Kim cương | C62: Pin kim loại, Đế lót ly in hình Gà Learning | F62: Hanoi
A63: thanhtuan.nguyen@garena.vn | B63: Gà chăm Kim cương | C63: Pin kim loại, Đế lót ly in hình Gà Learning | F63: Ho Chi Minh
A64: huuthinh.nguyen@garena.vn | B64: Gà chăm Kim cương | C64: Pin kim loại, Đế lót ly in hình Gà Learning | D64: Standee hình Gà | F64: Hanoi
A65: vanhiep.mai@garena.vn | B65: Gà chăm Kim cương | C65: Pin kim loại, Đế lót ly in hình Gà Learning | F65: Hanoi
A66: minhtri.le@garena.vn | B66: Gà chăm Kim cương | C66: Pin kim loại, Đế lót ly in hình Gà Learning | F66: Ho Chi Minh
A67: anhkhoa.le@garena.vn | B67: Gà chăm Kim cương | C67: Pin kim loại, Đế lót ly in hình Gà Learning | F67: Ho Chi Minh
A68: thuyquynh.luong@garena.vn | B68: Gà chăm Kim cương | C68: Đế lót ly in hình Gà Learning | F68: Hanoi
A69: ngocminh.le@garena.vn | B69: Gà chăm Tân thủ | C69: Pin kim loại | F69: Ho Chi Minh
A70: minhtri@garena.vn | B70: Gà chăm Tân thủ | C70: Pin kim loại | D70: Đế lót ly in hình Gà Learning | F70: Ho Chi Minh
A71: manhlinh.nguyen@garena.vn | B71: Gà chăm Tân thủ | C71: Pin kim loại | F71: Ho Chi Minh
A72: vananh.tran@garena.vn | B72: Gà chăm Tân thủ | C72: Pin kim loại | F72: Ho Chi Minh
A73: ngocthanh.nguyen@garena.vn | B73: Gà chăm Tân thủ | C73: Pin kim loại | D73: Đế lót ly in hình Gà Learning | F73: Ho Chi Minh
A74: linhtrang.tran@garena.vn | B74: Gà chăm Tân thủ | C74: Pin kim loại | F74: Hanoi
A75: nhutanh.ho@garena.vn | B75: Gà chăm Tân thủ | C75: Pin kim loại | F75: Ho Chi Minh
A76: minhtuan.dang@garena.vn | B76: Gà chăm Tân thủ | C76: Pin kim loại | F76: Ho Chi Minh
A77: tunganh.hoang@garena.vn | B77: Gà chăm Tân thủ | C77: Pin kim loại | F77: Hanoi
A78: thibinh.trinh@garena.vn | B78: Gà chăm Tân thủ | C78: Pin kim loại | F78: Ho Chi Minh
A79: anhtu.le@garena.vn | B79: Gà chăm Tân thủ | C79: Pin kim loại | F79: Hanoi
A80: hodong.huynh@garena.vn | B80: Gà chăm Tân thủ | C80: Pin kim loại | F80: Ho Chi Minh
A81: trungkien.tran@garena.vn | B81: Gà chăm Tân thủ | C81: Pin kim loại | F81: Hanoi
A82: hoanganh.duong@garena.vn | B82: Gà chăm Tân thủ | C82: Pin kim loại | F82: Hanoi
A83: tuannguyen.huynh@garena.vn | B83: Gà chăm Tân thủ | C83: Pin kim loại | F83: Ho Chi Minh
A84: anhphuong.nguyen@garena.vn | B84: Gà chăm Tân thủ | C84: Pin kim loại | F84: Ho Chi Minh
A85: tuyenchinh.vo@garena.vn | B85: Gà chăm Tân thủ | C85: Pin kim loại | F85: Ho Chi Minh
A86: thanhduy.huynh@garena.vn | B86: Gà chăm Tân thủ | C86: Pin kim loại | D86: Đế lót ly in hình Gà Learning | F86: Ho Chi Minh
A87: luong.vo@garena.vn | B87: Gà chăm Tân thủ | C87: Pin kim loại | F87: Ho Chi Minh
A88: xuanthai.hua@garena.vn | B88: Gà chăm Tân thủ | C88: Pin kim loại | F88: Ho Chi Minh
A89: vanhoang.nguyen@garena.vn | B89: Gà chăm Tân thủ | C89: Pin kim loại | F89: Hanoi
A90: hoaithuong.tran@garena.vn | B90: Gà chăm Tân thủ | C90: Pin kim loại | F90: Hanoi
A91: duytu.vo@garena.vn | B91: Gà chăm Tân thủ | C91: Pin kim loại | F91: Hanoi
A92: kieuanh.nguyen@garena.vn | B92: Gà chăm Tân thủ | C92: Pin kim loại | F92: Hanoi
A93: thitrang.nguyen@garena.vn | B93: Gà chăm Tân thủ | C93: Pin kim loại | F93: Ho Chi Minh
A94: nhi.nguyen@garena.vn | B94: Gà chăm Tân thủ | C94: Pin kim loại | F94: Hanoi

Sheet Sheet14
A1: viethop.nguyen@garena.vn | B1: Gà chăm Tinh Anh
A2: phuongthao.dao@garena.vn | B2: Gà chăm Kim cương
A3: huongly.dang@garena.vn | B3: Gà chăm Kim cương
A4: maiphuong.pham@garena.vn | B4: Gà chăm Kim cương
A5: ducthao.tran@garena.vn | B5: Gà chăm Kim cương
A6: tienduc.nguyen@garena.vn | B6: Gà chăm Kim cương
A7: quoctuan.tran@garena.vn | B7: Gà chăm Kim cương
A8: phuongthao.hoang@garena.vn | B8: Gà chăm Kim cương
A9: lanchi.vu@garena.vn | B9: Gà chăm Kim cương
A10: khaikien.duong@garena.vn | B10: Gà chăm Kim cương
A11: thuanh.hotran@garena.vn | B11: Gà chăm Kim cương
A12: minhtri.hoang@garena.vn | B12: Gà chăm Kim cương
... A53: minhkhoi.nguyen@garena.vn | B53: Gà chăm Cao thủ

Sheet Data Learning Hours chi tiết 20
A1: Mail | B1: Sum of Learning Hours | C1: Course Name | D1: Type | E1: Date Start | F1: Date End
A2: hongduc.dao@garena.vn | B2: 65 | C2: English Online Course (WSE) | D2: Training Budget Sponsor | E2: 45524 | F2: 45708
A3: vananh@garena.vn | B3: 6 | C3: Tax Update 2025 | D3: Training Budget Sponsor | E3: 45706 | F3: 45706
A4: phuonglien.ngo@garena.vn | B4: 6 | C4: Tax Update 2025 | D4: Training Budget Sponsor | E4: 45706 | F4: 45706
A5: thithanh.le@garena.vn | B5: 6 | C5: Tax Update 2025 | D5: Training Budget Sponsor | E5: 45706 | F5: 45706
A6: thutrang.tran@garena.vn | B6: 6 | C6: Tax Update 2025 | D6: Training Budget Sponsor | E6: 45706 | F6: 45706
A7: thutrang.nguyen@garena.vn | B7: 6 | C7: Tax Update 2025 | D7: Training Budget Sponsor | E7: 45706 | F7: 45706
A8: thutrang.nguyenthi@garena.vn | B8: 6 | C8: Tax Update 2025 | D8: Training Budget Sponsor | E8: 45706 | F8: 45706
A9: thuyan.nguyen@garena.vn | B9: 6 | C9: Tax Update 2025 | D9: Training Budget Sponsor | E9: 45706 | F9: 45706
A10: thuyquynh.luong@garena.vn | B10: 5 | C10: Tax Update 2025 | D10: Training Budget Sponsor | E10: 45706 | F10: 45706
A11: thiloan.nguyen@garena.vn | B11: 3 | C11: Tax Update 2025 | D11: Training Budget Sponsor | E11: 45706 | F11: 45706
A12: huyenanh.phan@garena.vn | B12: 12.5 | C12: Marketing Analytics | D12: Training Budget Sponsor | E12: 45663 | F12: 45705
A13: traanh.au@garena.vn | B13: 12.5 | C13: Marketing Analytics | D13: Training Budget Sponsor | E13: 45663 | F13: 45705
A14: lenam.to@garena.vn | B14: 12.5 | C14: Marketing Analytics | D14: Training Budget Sponsor | E14: 45663 | F14: 45705

Sheet Trang tính7
A1: agreement | B1: comments | C1: courseAuthor | D1: courseCertificate | E1: courseDuration | F1: courseEffect | G1: courseEffectByManager | H1: courseEndDate | I1: courseFee | J1: courseFeeByRec | K1: courseFreq | L1: courseName | M1: coursePaymentByRec | N1: courseSMART | O1: courseStartDate | P1: courseTypeByRec | Q1: courseWeb | R1: divider1 | S1: divider2 | T1: email | U1: form_name | V1: id | W1: lastUpdatedAt | X1: po | Y1: raisedAt | Z1: reason | AA1: status | AB1: subsidizeLevel | AC1: subsidizeType | AD1: team
A2: TRUE | C2: DataPot | D2: TRUE | E2: Test | F2: Test | G2: Test | H2: 45099 | I2: 5720000 | J2: 50% chi phí theo khóa học - tương ứng 2.000.000 VNĐ (đã bao gồm 10% VAT) | K2: Test | L2: PowerBI Data Analytics | M2: Khóa học cấp thiết hỗ trợ theo khóa học (tối đa 17tr/khóa; 34tr/năm) | N2: Test | O2: 45095 | P2: X% chi phí theo khóa học - tương ứng X VNĐ (đã bao gồm 10% VAT) | Q2: https://datapot.vn/khoa-hoc/power-bi-advanced-data-modeling-and-dax/ | R2: X | S2: X | T2: minhngoc.phamnguyen@garena.vn | U2: Đăng ký Hỗ trợ chi phí Đào tạo | V2: 36755 | W2: 45421 | X2: minhngoc.phamnguyen@garena.vn | Y2: 45093 | Z2: X | AA2: closed | AB2: Cấp thiết: Trực tiếp nâng cao kỹ năng và kiến thức trong lĩnh vực chuyên môn của nhân viên | AC2: Loại A: Các khóa học cấp chứng chỉ / Hội thảo / Hội nghị / Văn bằng hoặc Bằng cấp (chỉ dành cho học phần) / Nền tảng khóa học trực tuyến mở ví dụ: Udemy | AD2: RECRUITMENT_AND_TRAINING
A3: TRUE | C3: Adobe | I3: 10000000 | J3: ABC | L3: Photoshop 2023 | M3: ABC | P3: ABC | Q3: https://docs.google.com/presentation/d/1UI3grUkAxKz3RrcCHlg0z5Tb2qab2BZ1XzZoukk2wtw/edit#slide=id.g24d0c03fa55_0_2 | R3: Phần 1: Tổng quan nhu cầu của nhân sự | S3: Phần 2: Đề xuất từ bộ phận Đào tạo | T3: minhngoc.phamnguyen@garena.vn | U3: Đăng ký Hỗ trợ chi phí Đào tạo | V3: 36786 | W3: 45143 | X3: minhngoc.phamnguyen@garena.vn | Y3: 45097 | Z3: ABC | AA3: closed | AB3: Cấp thiết: Trực tiếp nâng cao kỹ năng và kiến thức trong lĩnh vực chuyên môn của nhân viên | AC3: Loại B: Tài liệu đọc (Sách điện tử / Sách / Bài báo) | AD3: RECRUITMENT_AND_TRAINING
A4: TRUE | C4: Adobe | D4: TRUE | E4: X | F4: X | G4: X | H4: 45099 | I4: 10000000 | J4: X | K4: X | L4: Photoshop 2023 | M4: X | N4: X | O4: 45097 | P4: X | Q4: https://docs.google.com/presentation/d/1UI3grUkAxKz3RrcCHlg0z5Tb2qab2BZ1XzZoukk2wtw/edit#slide=id.g24d0c03fa55_0_2 | R4: X | S4: X | T4: minhngoc.phamnguyen@garena.vn | U4: Đăng ký Hỗ trợ chi phí Đào tạo | V4: 36788 | W4: 45143 | X4: minhngoc.phamnguyen@garena.vn | Y4: 45097 | Z4: X | AA4: closed | AB4: Cấp thiết: Trực tiếp nâng cao kỹ năng và kiến thức trong lĩnh vực chuyên môn của nhân viên | AC4: Loại A: Các khóa học cấp chứng chỉ / Hội thảo / Hội nghị / Văn bằng hoặc Bằng cấp (chỉ dành cho học phần) / Nền tảng khóa học trực tuyến mở ví dụ: Udemy | AD4: RECRUITMENT_AND_TRAINING
A5: TRUE | C5: DataPot | D5: TRUE | E5: 1h | F5: Test | H5: 45107 | I5: 5720000 | J5: TEst | K5: Test | L5: PowerBI Data Analytics | M5: Test | N5: Test | O5: 45075 | P5: Test | Q5: https://datapot.vn/khoa-hoc/power-bi-advanced-data-modeling-and-dax/ | R5: x | S5: Đề xuất | T5: hoaithuong.tran@garena.vn | U5: Đăng ký Hỗ trợ chi phí Đào tạo | V5: 36793 | W5: 45097 | X5: hoaithuong.tran@garena.vn | Y5: 45097 | Z5: NA | AA5: closed | AB5: Cấp thiết: Trực tiếp nâng cao kỹ năng và kiến thức trong lĩnh vực chuyên môn của nhân viên | AC5: Loại A: Các khóa học cấp chứng chỉ / Hội thảo / Hội nghị / Văn bằng hoặc Bằng cấp (chỉ dành cho học phần) / Nền tảng khóa học trực tuyến mở ví dụ: Udemy | AD5: RECRUITMENT_AND_TRAINING
A6: TRUE | B6: Em gửi thông báo kết quả phê duyệt + hướng dẫn đăng ký mua & claim chi phí mua tài liệu nhé ạ: https://drive.google.com/file/d/1btSKE-2nWabJ0IRbUIxCXSdamwiXbe6e/view?usp=drive_link | J6: 100% chi phí của tài liệu - tương ứng 3.500.000 VNĐ | M6: Nhân viên tự trả tiền trước và claim theo mã dự án training | P6: Hạng mục cấp thiết hỗ trợ theo tài liệu (tối đa 17tr/khóa hoặc tài liệu; tối đa 34tr/năm) | R6: Chi tiết nhu cầu của nhân sự đề xuất | S6: Chi tiết đề xuất từ bộ phận Đào tạo (dựa trên chính sách Hỗ trợ chi phí Đào tạo của Công ty) | T6: vananh.le@garena.vn | U6: Đăng ký Hỗ trợ chi phí Đào tạo | V6: 36813 | W6: 45152 | X6: vananh.le@garena.vn | Y6: 45097 | Z6: BP Đào tạo đề xuất | AA6: closed | AB6: Cấp thiết: Trực tiếp nâng cao kỹ năng và kiến thức trong lĩnh vực chuyên môn của nhân viên | AC6: Loại B: Tài liệu đọc (Sách điện tử / Sách / Bài báo) | AD6: HRBP
A7: TRUE | B7: Account học online, team C&B sử dụng chung | C7: VCCI | D7: TRUE | E7: 2 ngày | F7: Update chính sách quy định của BLLĐ đảm bảo tính compliance các chính sách/hồ sơ liên quan đến lao động của Công ty. Giảm thiểu tối đa các sai sót khi có thanh tra. | H7: 45157 | I7: 1000000 VND | J7: 100% chi phí của tài liệu - tương ứng 1.000.000 VND | L7: CHÍNH SÁCH LAO ĐỘNG TIỀN LƯƠNG và BẢO HIỂM XÃ HỘI 2023 | M7: Nhân viên tự trả tiền trước và claim theo mã dự án training | N7: S: củng cố/cập nhật các quy định mới liên quan đến tính compliance của các chính sách nhân sự M: không có chính sách/quy định nào trái luật A: đảm bảo hệ thống chính sách/văn bản nhân sự đúng đủ R: liên quan đến các chính sách nhân sự khi hướng dẫn nhân viên/thanh kiểm tra T: đánh giá qua các kỳ rà soát chính sách quy định nhân sự | O7: 45156 | P7: Hạng mục cấp thiết hỗ trợ theo khóa (tối đa 17tr/khóa; tối đa 34tr/năm) | Q7: https://edu.vcciesp.vn/chinh.sach.lao.dong.2023?fbclid=IwAR0HunO6XFHW1F_JhHwNQEOoVUKkv1UKCF5BZPHlCqNmZHQetbQuf0DvU0g | R7: Chi tiết nhu cầu của nhân sự đề xuất | S7: Chi tiết đề xuất từ bộ phận Đào tạo (dựa trên chính sách Hỗ trợ chi phí Đào tạo của Công ty) | T7: myhanh.luu@garena.vn | U7: Đăng ký Hỗ trợ chi phí Đào tạo | V7: 37761 | W7: 45147 | X7: myhanh.luu@garena.vn | Y7: 45146 | Z7: BP Đào tạo đề xuất | AA7: closed | AB7: Cấp thiết: Trực tiếp nâng cao kỹ năng và kiến thức trong lĩnh vực chuyên môn của nhân viên | AC7: Loại A: Các khóa học cấp chứng chỉ / Hội thảo / Hội nghị / Văn bằng hoặc Bằng cấp (chỉ dành cho học phần) / Nền tảng khóa học trực tuyến mở ví dụ: Udemy | AD7: CNB
A8: TRUE | B8: Em gửi thông báo kết quả phê duyệt + hướng dẫn đăng ký mua & claim chi phí mua tài liệu nhé ạ: https://drive.google.com/file/d/15NrLZit4G19CexyGuyhzj90UUaACs6Wc/view?usp=sharing | C8: VCCI | D8: TRUE | E8: 2 ngày | F8: Update chính sách quy định của BLLĐ đảm bảo tính compliance các chính sách/hồ sơ liên quan đến lao động của Công ty. Giảm thiểu tối đa các sai sót khi có thanh tra. | H8: 45157 | I8: 1000000 vnd | J8: 100% chi phí của tài liệu - tương ứng 1.000.000 VND | L8: CHÍNH SÁCH LAO ĐỘNG TIỀN LƯƠNG và BẢO HIỂM XÃ HỘI 2023 | M8: Nhân viên tự trả tiền trước và claim theo mã dự án training | N8: S: củng cố/cập nhật các quy định mới liên quan đến tính compliance của các chính sách nhân sự M: không có chính sách/quy định nào trái luật A: đảm bảo hệ thống chính sách/văn bản nhân sự đúng đủ R: liên quan đến các chính sách nhân sự khi hướng dẫn nhân viên/thanh kiểm tra T: đánh giá qua các kỳ rà soát chính sách quy định nhân sự | O8: 45156 | P8: Hạng mục cấp thiết hỗ trợ theo khóa (tối đa 17tr/khóa; tối đa 34tr/năm) | Q8: https://edu.vcciesp.vn/chinh.sach.lao.dong.2023?fbclid=IwAR0HunO6XFHW1F_JhHwNQEOoVUKkv1UKCF5BZPHlCqNmZHQetbQuf0DvU0g | R8: Chi tiết nhu cầu của nhân sự đề xuất | S8: Chi tiết đề xuất từ bộ phận Đào tạo (dựa trên chính sách Hỗ trợ chi phí Đào tạo của Công ty) | T8: myhanh.luu@garena.vn | U8: Đăng ký Hỗ trợ chi phí Đào tạo | V8: 37771 | W8: 45194 | X8: myhanh.luu@garena.vn | Y8: 45147 | Z8: BP Đào tạo đề xuất | AA8: closed | AB8: Cấp thiết: Trực tiếp nâng cao kỹ năng và kiến thức trong lĩnh vực chuyên môn của nhân viên | AC8: Loại A: Các khóa học cấp chứng chỉ / Hội thảo / Hội nghị / Văn bằng hoặc Bằng cấp (chỉ dành cho học phần) / Nền tảng khóa học trực tuyến mở ví dụ: Udemy | AD8: CNB
A9: TRUE | B9: Em gửi thông báo kết quả phê duyệt + hướng dẫn đăng ký khóa học & claim chi phí nhé ạ: https://drive.google.com/file/d/1-v4xdO3ZwLAcKDR6lKMDvK7nCvE5kX6o/view?usp=sharing | C9: DataPot | D9: TRUE | E9: 16 buổi - 32 giờ học | F9: Khóa học giúp đạt được các kỹ năng: - Nhập làm sạch và chuyển đổi dữ liệu - Mô hình hóa dữ liệu cho hiệu suất và khả năng mở rộng - Thiết kế và tạo báo cáo để phân tích dữ liệu - Áp dụng và thực hiện phân tích báo cáo nâng cao - Quản lý và chia sẻ nội dung báo cáo - Tạo báo cáo được phân trang trong Power BI Các kỹ năng trên bổ trợ trực tiếp cho công việc phân tích dữ liệu nhằm phát triển công ty. | H9: 45226 | I9: 6.048.000 VNĐ (bao gồm 8% VAT - cập nhật theo báo giá mới nhất của Datapot) | J9: 100% chi phí của khóa học - tương ứng 6.048.000 VNĐ | K9: 2 buổi 1 tuần | L9: ANALYZING DATA WITH POWER BI (Fresher) | M9: Nhân viên tự trả tiền trước và claim theo mã dự án training | N9: - S: Bổ sung kiến thức phân tích dữ liệu bằng công cụ Power BI để phục vụ công việc tracking data - M: Đạt mục tiêu xử lý dữ liệu sạch có ý nghĩa để đưa ra quyết định next step phù hợp với team - A: Bắt tay vào cùng phân tích dữ liệu với anh Hải Sơn càng sớm càng tốt - R: Xử lý dữ liệu để đưa ra quyết định phù hợp với định hướng của con game và công ty - T: Hoàn thành khóa học trong 2 tháng ứng dụng luôn vào công việc => Có khả năng phân tích dữ liệu từ tháng 11 (hoặc sớm hơn). | O9: 45174 | P9: Hạng mục cấp thiết hỗ trợ theo tài liệu (tối đa 17tr/khóa; tối đa 34tr/năm) | Q9: https://datapot.vn/khoa-hoc/da-100-analyzing-data-with-power-bi/ | R9: Chi tiết nhu cầu của nhân sự đề xuất | S9: Chi tiết đề xuất từ bộ phận Đào tạo (dựa trên chính sách Hỗ trợ chi phí Đào tạo của Công ty) | T9: huyenanh.phan@garena.vn | U9: Đăng ký Hỗ trợ chi phí Đào tạo | V9: 37945 | W9: 45244 | X9: huyenanh.phan@garena.vn | Y9: 45156 | Z9: BP Đào tạo đề xuất | AA9: approving | AB9: Cấp thiết: Trực tiếp nâng cao kỹ năng và kiến thức trong lĩnh vực chuyên môn của nhân viên | AC9: Loại A: Các khóa học cấp chứng chỉ / Hội thảo / Hội nghị / Văn bằng hoặc Bằng cấp (chỉ dành cho học phần) / Nền tảng khóa học trực tuyến mở ví dụ: Udemy | AD9: AOV
A10: TRUE | C10: Project Management Institute | D10: TRUE | E10: N/A | F10: Hiện tại để tăng cường tối ưu hiệu quả hoạt động vận hành giảm bớt nhân sự làm các công việc thủ công như trước kia nên nhu cầu gia tăng nhiều dự án phát triển phần mềm dài hạn có tính chất phức tạp đòi hỏi yêu cầu quản lý dự án ở mức nâng cao và chuyên nghiệp hơn. Do đó cần học thêm khoá học này để áp dụng các mô hình quản lý dự án chuyên nghiệp học thêm nhiều technique để rút ngắn thời gian nâng cao hiệu suất giúp có thể đồng thời xử lý được nhiều dự án với chất lượng tốt hơn phục vụ tốt hơn cho nhu cầu của các team game và công ty. Ngoài ra khoá học cũng cũng cấp nhiều use case để có thể vận dụng trong nhiều tình huống thực tế tăng khả năng hài lòng của các thành viên tham gia dự án. | H10: 45473 | I10: 555 | J10: 100% chi phí của chứng chỉ - tương ứng $555 ~ 13 436 550 (tỉ giá: 1 USD = 24 210 VNĐ) - chưa tính các thuế phí liên quan đến thanh toán ra nước ngoài & có thể điều chỉnh về tỉ giá tại thời điểm thanh toán | L10: Project Management Professional (PMP)® | M10: Nhân viên tự trả tiền trước và claim theo mã dự án training | N10: - S: Tôi sẽ tăng cường các kỹ năng quản lý dự án hiệu quả hơn - M: Tôi sẽ đặt mục tiêu nâng cao kỹ năng trên tất cả các phương diện như con người quá trình và hiệu quả kinh doanh - R: Tăng cường hiệu quả trong việc quản lý dự án chuyên nghiệp - T: Tôi sẽ đạt được điều này trong sáu tháng tới => Tôi sẽ hoàn thành chứng chỉ vào tháng 6 năm 2024 | O10: 45281 | P10: Hạng mục cấp thiết hỗ trợ theo tài liệu (tối đa 17tr/khóa; tối đa 34tr/năm) | Q10: https://www.pmi.org/certifications/project-management-pmp | R10: Chi tiết nhu cầu của nhân sự đề xuất | S10: Chi tiết đề xuất từ bộ phận Đào tạo (dựa trên chính sách Hỗ trợ chi phí Đào tạo của Công ty) | T10: dinhphuc.luu@garena.vn | U10: Đăng ký Hỗ trợ chi phí Đào tạo | V10: 40200 | W10: 45499 | X10: dinhphuc.luu@garena.vn | Y10: 45281 | Z10: BP Đào tạo đề xuất | AA10: closed | AB10: Cấp thiết: Trực tiếp nâng cao kỹ năng và kiến thức trong lĩnh vực chuyên môn của nhân viên | AC10: Loại A: Các khóa học cấp chứng chỉ / Hội thảo / Hội nghị / Văn bằng hoặc Bằng cấp (chỉ dành cho học phần) / Nền tảng khóa học trực tuyến mở ví dụ: Udemy | AD10: CODE
A11: TRUE | B11: Em gửi thông báo kết quả phê duyệt + hướng dẫn đăng ký khóa học & claim chi phí nhé ạ: https://drive.google.com/file/d/1wY6zNRr4ixYm7Nd_ecchXqP5f0nveO7T/view?usp=sharing | C11: Công ty TNHH Phát Triển aroma - Aroma Tiếng Anh cho người đi làm | D11: TRUE | E11: 40 giờ | F11: 1. Đặc thù vị trí công việc làm việc với các khu vực khác đối tác nước ngoài. Nâng cao trình độ tiếng anh để nâng cao khả năng giao tiếp trao đổi trong tất cả các dự án. | H11: 45442 | I11: 16.380.000 VNĐ | J11: 50% chi phí của chứng chỉ - tương ứng 8.190.000 VNĐ | K11: 2-3 buổi/tuần | L11: Khóa học tiếng anh Intermediate level | M11: Nhân viên tự trả tiền trước và claim theo mã dự án training | N11: - S: Tăng cường kỹ năng giao tiếp khi làm việc với local team hay đối tác nước ngoài. - M: Sau khóa học ngắn hạn có thể xác định được trình độ đặt mục tiêu cải thiện ở mực độ cao hơn và có target rõ ràng bằng chứng chỉ IELTS. - A: Xác định trình độ mục tiêu cho chứng chỉ IELTS. - R: Tối ưu giao tiếp trong giải đoạn chuẩn bị giải đấu APL 2024 tại Thái Lan. - T: Đạt được điều này trong 6 tháng tới khóa học này là bước đầu để cải thiện lại nền tảng ngữ pháp. => Nâng cao kỹ năng giao tiếp khi làm việc bằng tiếng anh giảm thiểu thời gian khi chuẩn bị các tài liệu bằng tiếng anh (report review sop...etc) | O11: 45300 | P11: Hạng mục bổ trợ - tối đa 8.5 triệu VND/ nội dung | Q11: http://aroma.vn/tieng-anh-cho-nguoi-di-lam/ | R11: Chi tiết nhu cầu của nhân sự đề xuất | S11: Chi tiết đề xuất từ bộ phận Đào tạo (dựa trên chính sách Hỗ trợ chi phí Đào tạo của Công ty) | T11: hongduc.le@garena.vn | U11: Đăng ký Hỗ trợ chi phí Đào tạo | V11: 40434 | W11: 45306 | X11: hongduc.le@garena.vn | Y11: 45295 | Z11: BP Đào tạo đề xuất | AA11: processing | AB11: Bổ trợ: Bổ trợ cho các kỹ năng và kiến thức trong lĩnh vực chuyên môn của nhân viên | AC11: Loại A: Các khóa học cấp chứng chỉ / Hội thảo / Hội nghị / Văn bằng hoặc Bằng cấp (chỉ dành cho học phần) / Nền tảng khóa học trực tuyến mở ví dụ: Udemy | AD11: AOV
A12: TRUE | C12: Học viện Công nghệ Bưu Chính Viễn Thông | D12: TRUE | E12: 4 5 năm | F12: Trong quản lý dự án kiến thức Khoa học Máy tính sẽ giúp tôi rất nhiều như quá trình lập kế hoạch đánh giá hiệu quả lựa chọn giải pháp phù hợp. Điều này sẽ tăng cường khả năng ra quyết định thông minh tối ưu hóa quá trình quản lý và mang lại hiệu suất cao cho dự án. Đặc biệt với sự xuất hiện nhiều dự án mới đòi hỏi nhiều kiến thức chuyên sâu về khoa học máy tính như dự án về AI Blockchain kiến thức vững về Khoa học Máy tính mang lại nền tảng vững chắc cho công việc hiệu quả hơn. Ngoài ra sự hiểu biết vững về Khoa học Máy tính giúp tôi làm việc hiệu quả hơn với đội ngũ dự án cả local và region dễ dàng trao đồi bàn bạc và đưa ra đánh giá và ước tính chính xác hơn cũng như đề xuất những giải pháp sáng tạo. Từ đó tôi có thể quản lý nhiều dự án công nghệ phức tạp nhanh chóng và hiệu quả hơn góp phần hỗ trợ công ty giải quyết nhiều vấn đề về business tiết kiệm chi phí vận hành và tối đa hoá doanh thu. | H12: 46600 | I12: 62000000 | L12: Kỹ sư Khoa học máy tính | N12: - S: Tôi sẽ nâng cao kiến thức chuyên môn về các phương pháp phát triển phần mềm nâng cao khả năng quản lý các dự án phần mềm một cách hiệu quả. - M: Tôi sẽ đặt mục tiêu nâng cao kỹ năng trên tất cả các phương diện như kiến thức kỹ năng giải quyết vấn đề nắm bắt nền tảng công nghệ mới - R: cung cấp sự hiểu biết kỹ thuật sâu sắc hơn cho phép tôi đóng góp một cách chiến lược hơn cho các dự án phù hợp với mục tiêu dài hạn của công ty - T: Tôi sẽ đạt được điều này trong ba năm tới => Tôi sẽ hoàn thành vào năm 2027 | O12: 45047 | Q12: https://daotao.ptit.edu.vn/nganhhoc/7480101 | T12: dinhphuc.luu@garena.vn | U12: Đăng ký Hỗ trợ chi phí Đào tạo | V12: 40825 | W12: 45309 | X12: dinhphuc.luu@garena.vn | Y12: 45308 | Z12: Update | AA12: closed | AB12: Cấp thiết: Trực tiếp nâng cao kỹ năng và kiến thức trong lĩnh vực chuyên môn của nhân viên | AC12: Loại A: Các khóa học cấp chứng chỉ / Hội thảo / Hội nghị / Văn bằng hoặc Bằng cấp (chỉ dành cho học phần) / Nền tảng khóa học trực tuyến mở ví dụ: Udemy | AD12: CODE
A13: TRUE | B13: Em gửi thông báo kết quả phê duyệt + hướng dẫn đăng ký khóa học & claim chi phí nhé ạ: https://drive.google.com/file/d/1dWty4xDaatC5xcbKbL5lMRyDRQumfo9y/view?usp=drive_link | C13: DataPot | D13: TRUE | E13: 16 buổi | F13: Xử lý data cho team AOV Esports Regional và 3 Local teams: VN/TH/TW. Từ đó đưa ra phân tích dữ liệu và kế hoạch marketing tốt hơn cho team Esports. | H13: 45435 | I13: 6.264.000 VNĐ (đã bao gồm VAT) | J13: 100% chi phí của khóa học - tương ứng 6.264.000 VNĐ | K13: 2 buổi/tuần | L13: PowerBI Data Analytics | M13: Nhân viên tự trả tiền trước và claim theo mã dự án training | N13: - S: Bổ sung kiến thức nâng cao phân tích dữ liệu bằng công cụ Power BI để phục vụ công việc tracking data - M: Đạt mục tiêu xử lý dữ liệu sạch có ý nghĩa để đưa ra quyết định next step phù hợp với team - A: Đưa ra phân tích & định hướng tốt hơn cho AOV Esports Regional Team và 2 Locals team còn lại: TH/TW - R: Xử lý dữ liệu để đưa ra quyết định phù hợp với định hướng của con game và công ty - T: Hoàn thành khóa học trong 2 tháng ứng dụng nâng cao được vào công việc=> Có khả năng Xử lý data nâng cao cho team AOV Esports Regional và 3 Local teams: VN/TH/TW | O13: 45379 | P13: Hạng mục cấp thiết - tối đa 17 triệu VND/ khóa/năm | Q13: https://datapot.vn/khoa-hoc/da-100-analyzing-data-with-power-bi/ | R13: Chi tiết nhu cầu của nhân sự đề xuất | S13: Chi tiết đề xuất từ bộ phận Đào tạo (dựa trên chính sách Hỗ trợ chi phí Đào tạo của Công ty) | T13: quochung.khong@garena.vn | U13: Đăng ký Hỗ trợ chi phí Đào tạo | V13: 41536 | W13: 45364 | X13: quochung.khong@garena.vn | Y13: 45357 | Z13: BP Đào tạo đề xuất | AA13: processing | AB13: Cấp thiết: Trực tiếp nâng cao kỹ năng và kiến thức trong lĩnh vực chuyên môn của nhân viên | AC13: Loại A: Các khóa học cấp chứng chỉ / Hội thảo / Hội nghị / Văn bằng hoặc Bằng cấp (chỉ dành cho học phần) / Nền tảng khóa học trực tuyến mở ví dụ: Udemy | AD13: AOV
A14: TRUE | B14: #ERROR! | C14: Udemy | D14: TRUE | E14: 10 hours | F14: Hiện tại vấn đề cải thiện trải nghiệm của người dùng chưa được chú trọng do đó cần cập nhật kiến thức và sharing đến các PO desingers để cùng phối hợp đưa ra sản phẩm mang tới trải nghiệm tốt hơn cho người dùng đặc biệt trên phiên bản mobile. | H14: 45373 | I14: 2199000 | L14: User Experience Design Fundamentals | N14: - S: Ôn tập và phát triển kiến thức cho buổi sharing sắp tới - M: Tôi sẽ đặt mục tiêu nâng cao kiến thức đồng thời phổ biến kiến thức cho các team khác - R: Tăng cường hiệu quả trong việc cải thiện trải nghiệm người dùng trên mobile - T: Tôi sẽ đạt được điều này trong một tháng tới => Tôi sẽ dự kiến có buổi sharing vào tháng 4 | O14: 45373 | Q14: https://www.udemy.com/course/user-experience-design-fundamentals/ | T14: dinhphuc.luu@garena.vn | U14: Đăng ký Hỗ trợ chi phí Đào tạo | V14: 41877 | W14: 45387 | X14: dinhphuc.luu@garena.vn | Y14: 45373 | AA14: closed | AB14: Cấp thiết: Trực tiếp nâng cao kỹ năng và kiến thức trong lĩnh vực chuyên môn của nhân viên | AC14: Loại A: Các khóa học cấp chứng chỉ / Hội thảo / Hội nghị / Văn bằng hoặc Bằng cấp (chỉ dành cho học phần) / Nền tảng khóa học trực tuyến mở ví dụ: Udemy | AD14: CODE
A15: TRUE | B15: Em gửi thông báo kết quả phê duyệt + hướng dẫn đăng ký khóa học & claim chi phí nhé ạ: https://drive.google.com/file/d/1yHL7KDjuiMr3p7JbthSXRnzCQ-Ah5hL2/view?usp=drive_link | C15: Coursera | D15: TRUE | E15: 1 month | F15: Python giúp phân tích dữ liệu tạo trực quan hóa dữ liệu giúp phân tích dữ liệu hiệu quả hơn => Hỗ trợ tốt trong việc thống kê dữ lliệu và sự so sánh dữ liệu giữa các campaign tốt hơn giúp việc planning cho các campaign sau hiệu quả hơn | H15: 45395 | I15: 49$ | J15: 50% của khóa học - tương ứng 673.241 VNĐ (đã bao gồm 5% VAT và 5% CIT) | K15: 3 days per week | L15: Python Basic | M15: Nhân viên tự trả tiền trước và claim theo mã dự án training | N15: S: Tìm hiểu Python để hỗ trợ tôi trong việc phát triển các data tool phục vụ hiệu quả trobg quá trình làm việc dễ dàng hơn trong việc trao đổi với code team. M: Giảm 20 - 30% thời gian planning manage scope công việc và check data trong quá trình vận hành campaign. A: Tôi đặt mục tiêu tạo ra 1 hệ thống thống kê data và kiểm soát scope công việc + planning dễ follow up hơn. R: Kiểm soát scope tốt đẻ tăng hiệu quả công việc giảm bớt thời gian execute T: Dự kiến có logic rõ ràng trong 1 tháng sau khi hoàn thành khóa học sau đó sẽ tiến hành các bước tiếp theo với các team liên quan | O15: 45364 | P15: Hạng mục bổ trợ - tối đa 8.5 triệu VND / nội dung | Q15: https://www.coursera.org/learn/python | R15: Chi tiết nhu cầu của nhân sự đề xuất | S15: Chi tiết đề xuất từ bộ phận Đào tạo (dựa trên chính sách Hỗ trợ chi phí Đào tạo của Công ty) | T15: phuonglinh.pham@garena.vn | U15: Đăng ký Hỗ trợ chi phí Đào tạo | V15: 42062 | W15: 45397 | X15: phuonglinh.pham@garena.vn | Y15: 45387 | Z15: BP Đào tạo đề xuất | AA15: processing | AB15: Bổ trợ: Bổ trợ cho các kỹ năng và kiến thức trong lĩnh vực chuyên môn của nhân viên | AC15: Loại A: Các khóa học cấp chứng chỉ / Hội thảo / Hội nghị / Văn bằng hoặc Bằng cấp (chỉ dành cho học phần) / Nền tảng khóa học trực tuyến mở ví dụ: Udemy | AD15: FC Online
A16: TRUE | B16: Em gửi thông báo kết quả phê duyệt + hướng dẫn đăng ký khóa học & claim chi phí nhé ạ: https://drive.google.com/file/d/1H9sgA00u5V181zTB8-MgzeN-0X4CRal1/view?usp=drive_link | C16: ELITE PR SCHOOL | D16: TRUE | E16: 6 buổi | F16: Đạt được các mục tiêu theo goal setting committed | H16: 45409 | I16: 6.000.000 VNĐ (chưa VAT) | J16: 100% của khóa học - tương ứng 6.000.000 VNĐ (chưa VAT) | L16: Xây dựng văn hóa doanh nghiệp và hệ thống truyền thông nội bộ | M16: Nhân viên tự trả tiền trước và claim theo mã dự án training | N16: - S: Thiết kế các hoạt động TTNB thiết thực thu hút và tăng engagement rate trong năm 2024 (~90%) - M: Xây dựng được tiêu chí phương thức đo lường và đánh giá hiệu quả các hoạt động TTNB - A: Biết cách khảo sát phân tích đặc trưng văn hoá từ đó xây dựng được nền móng và các trụ cột văn hoá doanh nghiệp. Nắm được cấu trúc hệ thống quy trình hoạch định kế hoạch truyền thông nội bộ hợp lý. - R: Cải thiện được các hoạt động nội bộ sẽ dẫn đến sự gắn kết giữa các nhân viên và công ty. Ngoài ra đồng bộ thông tin truyền thông nội bộ cho thấy được sự chuyên nghiệp và nhất quán từ công ty -> tiền đề để xây dựng văn hoa riêng.- T: Cải thiện được đo lường từ số lượng và chất lượng theo từng quý/ từng sự kiện và dự án truyền thông | O16: 45402 | P16: Hạng mục cấp thiết - tối đa 17 triệu VND / nội dung | Q16: https://eliteprschool.edu.vn/van-hoa-doanh-nghiep-ttnb/ | R16: Chi tiết nhu cầu của nhân sự đề xuất | S16: Chi tiết đề xuất từ bộ phận Đào tạo (dựa trên chính sách Hỗ trợ chi phí Đào tạo của Công ty) | T16: linhtrang.tran@garena.vn | U16: Đăng ký Hỗ trợ chi phí Đào tạo | V16: 42110 | W16: 45397 | X16: linhtrang.tran@garena.vn | Y16: 45391 | Z16: Bổ sung thêm về mục tiêu học tập | AA16: processing | AB16: Cấp thiết: Trực tiếp nâng cao kỹ năng và kiến thức trong lĩnh vực chuyên môn của nhân viên | AC16: Loại A: Các khóa học cấp chứng chỉ / Hội thảo / Hội nghị / Văn bằng hoặc Bằng cấp (chỉ dành cho học phần) / Nền tảng khóa học trực tuyến mở ví dụ: Udemy | AD16: PEOPLE
A17: TRUE | B17: Em gửi thông báo kết quả phê duyệt + hướng dẫn đăng ký khóa học & claim chi phí nhé ạ: https://drive.google.com/file/d/1W-oXtcal3X3F_9Y3vswRaUOBNsoPKULw/view?usp=sharing | C17: Tomorrow marketers | D17: TRUE | E17: 12 buổi | F17: Cải thiện hệ thống tracking dữ liệu kết quả với KPI cho các hoạt động MKT của team. Training lại cho các thành viên trong team quy trình và mindset phân tích dữ liệu khi đưa ra quyết định trong các hoạt động MKT | H17: 45477 | I17: 5.750.000 VND | J17: 100% của khóa học - tương ứng 5.750.000 VNĐ (VAT 0%) | K17: 2 buổi/tuần | L17: Phân tích dữ liệu cho quyết định chiến lược | N17: S: Cải thiện hệ thống tracking dữ liệu kết quả với KPI cho các hoạt động MKT của team M: Đặt mục tiêu thu hút tổng new user và churn user back của FCO trong quý 2 đạt 1.2M A: Training lại cho các thành viên trong team quy trình và mindset phân tích dữ liệu khi đưa ra quyết định trong các hoạt động MKT R: Tăng trưởng người dùng cho thấy sự phát triển của tựa game T: Đạt được điều này trong 2 tháng tới sau đó đánh giá lại trước khi lập kế hoạch cho các bước tiếp theo | O17: 45435 | Q17: https://www.tomorrowmarketers.org/data-analysis-course | R17: Chi tiết nhu cầu của nhân sự đề xuất | S17: Chi tiết đề xuất từ bộ phận Đào tạo (dựa trên chính sách Hỗ trợ chi phí Đào tạo của Công ty) | T17: phuongthao.le@garena.vn | U17: Đăng ký Hỗ trợ chi phí Đào tạo | V17: 42269 | W17: 45516 | X17: phuongthao.le@garena.vn | Y17: 45401 | Z17: BP Đào tạo cập nhật đề xuất | AA17: processing | AB17: Cấp thiết: Trực tiếp nâng cao kỹ năng và kiến thức trong lĩnh vực chuyên môn của nhân viên | AC17: Loại A: Các khóa học cấp chứng chỉ / Hội thảo / Hội nghị / Văn bằng hoặc Bằng cấp (chỉ dành cho học phần) / Nền tảng khóa học trực tuyến mở ví dụ: Udemy | AD17: FC Online
A18: TRUE | B18: Em gửi hướng dẫn thanh toán và đăng ký, tham gia khóa học nhé ạ: https://drive.google.com/file/d/1NT6B4a9kn5QEY5wv14oA12rab6RIJ-bG/view?usp=sharing | C18: Datapot | D18: TRUE | E18: 16 buổi - 32 giờ | F18: Tăng hiệu suất làm việc tự chủ động quản lý và tìm ra những giải pháp tối ưu hơn cho dự án dựa trên số liệu | H18: 45510 | I18: 6000000 | J18: 100% của khóa học - tương ứng 6.480.000 VNĐ (bao gồm VAT 8%) | L18: PowerBI Data Analytics Basic | M18: Nhân viên tự trả tiền trước và claim theo mã dự án training | N18: Học lý thuyết bài bản về công cụ Power BI để sử dụng từ cơ bản tới nâng cao | O18: 45457 | P18: Hạng mục cấp thiết - tối đa 17 triệu VND / nội dung | Q18: https://datapot.vn/khoa-hoc/da-100-analyzing-data-with-power-bi/ | R18: Chi tiết nhu cầu của nhân sự đề xuất | S18: Chi tiết đề xuất từ bộ phận Đào tạo (dựa trên chính sách Hỗ trợ chi phí Đào tạo của Công ty) | T18: quanghuy.duong@garena.vn | U18: Đăng ký Hỗ trợ chi phí Đào tạo | V18: 42539 | W18: 45531 | X18: quanghuy.duong@garena.vn | Y18: 45420 | Z18: BP Đào tạo đề xuất | AA18: closed | AB18: Cấp thiết: Trực tiếp nâng cao kỹ năng và kiến thức trong lĩnh vực chuyên môn của nhân viên | AC18: Loại A: Các khóa học cấp chứng chỉ / Hội thảo / Hội nghị / Văn bằng hoặc Bằng cấp (chỉ dành cho học phần) / Nền tảng khóa học trực tuyến mở ví dụ: Udemy | AD18: 3KD
A19: TRUE | C19: W3School | D19: TRUE | E19: 1 Year | F19: Tự động hóa các task đang làm có khả năng giải quyết task chuyên sâu | H19: 45839 | I19: 149.99 USD/Year | J19: 50% của nội dung - tương ứng 1.894.599 (chưa bao gồm CIT và VAT) | L19: Subcribe Trang Web học các ngôn ngữ lập trình như Python | M19: Nhân viên tự trả tiền trước và claim theo mã dự án training | N19: Biết dùng thành thạo Python và SQL cho công việc | O19: 45444 | P19: Hạng mục cấp thiết - tối đa 17 triệu VND / nội dung | Q19: https://www.w3schools.com/ | R19: Chi tiết nhu cầu của nhân sự đề xuất | S19: Chi tiết đề xuất từ bộ phận Đào tạo (dựa trên chính sách Hỗ trợ chi phí Đào tạo của Công ty) | T19: anhkhoa.nguyen@garena.vn | U19: Đăng ký Hỗ trợ chi phí Đào tạo | V19: 42792 | W19: 45433 | X19: anhkhoa.nguyen@garena.vn | Y19: 45432 | Z19: BP Đào tạo đề xuất | AA19: closed | AB19: Bổ trợ: Bổ trợ cho các kỹ năng và kiến thức trong lĩnh vực chuyên môn của nhân viên | AC19: Loại A: Các khóa học cấp chứng chỉ / Hội thảo / Hội nghị / Văn bằng hoặc Bằng cấp (chỉ dành cho học phần) / Nền tảng khóa học trực tuyến mở ví dụ: Udemy | AD19: FF
A20: TRUE | B20: Em gửi hướng dẫn thanh toán và đăng ký, tham gia khóa học nhé ạ: https://drive.google.com/file/d/18tJB4Rt8SdGgjxlZPYbc5RUclvjFU5EB/view?usp=drive_link | C20: Talentnet | D20: TRUE | E20: 1 ngày | F20: Từ kiến thức của khóa học này có thể tư vấn những trend của thị trường tới business và tìm cách truyền thông/trao đổi về lương thưởng total rewards một cách hiệu quả hơn giúp cải thiện employee engagement và satisfaction về rewards | H20: 45555 | I20: 6 600 000 VND | J20: 100% của nội dung - tương ứng 6 600 000 (chưa bao gồm VAT) | K20: 1 lần | L20: Advanced Total Rewards Strategy | M20: Nhân viên tự trả tiền trước và claim theo mã dự án training | N20: Bổ sung kiến thức về Total Rewards của thị trường để phục vụ công việc phân tích đánh giá lương thưởng và communication một cách hiệu quả về lương thưởng | O20: 45555 | P20: Hạng mục cấp thiết - tối đa 17 triệu VND / nội dung | Q20: https://tln.talentnet.vn/eshop/advanced-total-rewards-strategy | R20: Chi tiết nhu cầu của nhân sự đề xuất | S20: Chi tiết đề xuất từ bộ phận Đào tạo (dựa trên chính sách Hỗ trợ chi phí Đào tạo của Công ty) | T20: vananh.le@garena.vn | U20: Đăng ký Hỗ trợ chi phí Đào tạo | V20: 42801 | W20: 45565 | X20: vananh.le@garena.vn | Y20: 45433 | Z20: BP Đào tạo đề xuất | AA20: processing | AB20: Cấp thiết: Trực tiếp nâng cao kỹ năng và kiến thức trong lĩnh vực chuyên môn của nhân viên | AC20: Loại A: Các khóa học cấp chứng chỉ / Hội thảo / Hội nghị / Văn bằng hoặc Bằng cấp (chỉ dành cho học phần) / Nền tảng khóa học trực tuyến mở ví dụ: Udemy | AD20: HRBP
A21: TRUE | B21: Đăng ký Hỗ trợ chi phí Đào tạo cho 5 thành viên phòng kế toán: 1. Ngô Thị Phương Liên 2. Lê Thị Thanh 3. Nguyễn Thị Thu Trang 4. Nguyễn Thu Trang 5. Trần Thu Trang,,Already got approval from ZY. @HR team, please help to support us. Thanks ,Do sát ngày nên slot cho ngày training gần nhất chỉ còn cho 2 người. Ngoài ra KPMG có tư vấn là khóa học không chuyên sâu, khóa học chỉ mang tính chất giới thiệu, chủ yếu cho người nước ngoài học nên team Finance quyết định không theo khóa học này nữa ạ. | C21: KPMG Việt Nam | D21: TRUE | E21: 3 tháng | F21: 1. Nâng cao chuyên môn nghiệp vụ về kế toán và lập báo cáo tài chính phù hợp với quy định về kế toán 2. Sau khi kết thúc khóa học các thành viên tham dự khóa học sẽ về training lại cho các thành viên trong phòng không tham dự khóa học để bổ sung và nâng cao kiến thức | H21: 45554 | I21: VND 10 625 000 (VND5tr x 5 pax x 50% x 85%) | J21: 100% - tương ứng 10 625 000 | K21: 2 buổi chiều mỗi tháng | L21: Chương trình đào tạo về Tài chính Kế toán năm 2024 tổ chức bởi KPMG | M21: Nhân viên tự trả tiền trước và claim theo mã dự án training | N21: - Bổ sung kiến thức nâng cao nghiệp vụ chuyên môn Tài chính kế toán - Rà soát lại các nghiệp vụ kế toán của công ty để điều chỉnh (nếu có) - Lập báo cáo tài chính năm phù hợp với quy định về kế toán - Hoàn thành khóa học trong 3 tháng ứng dụng nâng cao được vào công việc | O21: 45456 | P21: Hạng mục cấp thiết - tối đa 17 triệu VND / nội dung | Q21: https://29bb37d36e4a4a70a9a35b2b4966a3ce.marketingusercontent.com/m/view/r1lmePK07U4tJGijD3u6j9xP8UBTlFjXqxLckQUwKXIx | R21: Chi tiết nhu cầu của nhân sự đề xuất | S21: Chi tiết đề xuất từ bộ phận Đào tạo (dựa trên chính sách Hỗ trợ chi phí Đào tạo của Công ty) | T21: thutrang.nguyen@garena.vn | U21: Đăng ký Hỗ trợ chi phí Đào tạo | V21: 43172 | W21: 45456 | X21: thutrang.nguyen@garena.vn | Y21: 45450 | Z21: BP Đào tạo đề xuất | AA21: closed | AB21: Cấp thiết: Trực tiếp nâng cao kỹ năng và kiến thức trong lĩnh vực chuyên môn của nhân viên | AC21: Loại A: Các khóa học cấp chứng chỉ / Hội thảo / Hội nghị / Văn bằng hoặc Bằng cấp (chỉ dành cho học phần) / Nền tảng khóa học trực tuyến mở ví dụ: Udemy | AD21: FAC
A22: TRUE | B22: Em gửi hướng dẫn đăng ký học và thanh toán cho anh Thành nhé ạ: https://drive.google.com/file/d/1ujIzkd95wPsCv1yrrm684iP75HJ2s-U-/view?usp=drive_link | C22: TELOS.vn | D22: TRUE | E22: 4 tuần | F22: Figma có những ưu điểm vượt trội photoshop trong việc thiết kế UI. 1. rút ngắn thời gian giao tiếp & tracking khi Nhiều thành viên có thể làm chung trong một project. Requester làm wireframe và designer thiết kế & dev trên cùng 1 giao diện 2. (Chế độ dev mod) Dev có thể copy paste nhanh được mã màu font chữ size chữ khoảng cách lề… - Designer khi làm xong có thể check được luôn CSS trông như nào màu có lệch so với thiết kế không chữ có lệch không... siêu dễ để tự tinh chỉnh lại mà không cần chờ FE dev làm xong mới feedback 3. Plugin - Anima giúp con gà như e có thể export file thiết kế thành CSS trong 5s do máy làm. Dev có thể tận dụng 1 phần code được viết sẵn - Anima có thể export tất cả các file ảnh trong thiết kế thành file png/ jpg dev đỡ phải cắt từng tấm ảnh thủ công - Remove BG giúp tách background nhanh lẹ - Batch Styler giúp tạo style guideline nhanh lẹ có thể thay đổi màu sắc và font chữ hàng loạt thay vì chọn từng layer thủ công | H22: 45499 | I22: 4.400.000 VNĐ (đã bao gồm VAT) | J22: 100% - tương ứng 4.400.000 VNĐ | K22: 2 buổi 1 tuần | L22: Khoá học FIGMA DÀNH CHO DESIGNER/ DEVELOPER | M22: Nhân viên tự trả tiền trước và claim theo mã dự án training | N22: Mục tiêu khoá học: Nắm vững và Sử dụng thành thạo figma Ứng dụng figma vào công việc thiết kế UI ilua và UI cũng như các website của team. | O22: 45474 | P22: Hạng mục cấp thiết - tối đa 17 triệu VND / nội dung | Q22: https://telos.vn/khoa-hoc-thiet-ke-giao-dien-voi-figma/ | R22: Chi tiết nhu cầu của nhân sự đề xuất | S22: Chi tiết đề xuất từ bộ phận Đào tạo (dựa trên chính sách Hỗ trợ chi phí Đào tạo của Công ty) | T22: tienthanh.tran@garena.vn | U22: Đăng ký Hỗ trợ chi phí Đào tạo | V22: 43183 | W22: 45531 | X22: tienthanh.tran@garena.vn | Y22: 45450 | Z22: Nhập sai ngày kết thúc khoá học! | AA22: closed | AB22: Cấp thiết: Trực tiếp nâng cao kỹ năng và kiến thức trong lĩnh vực chuyên môn của nhân viên | AC22: Loại A: Các khóa học cấp chứng chỉ / Hội thảo / Hội nghị / Văn bằng hoặc Bằng cấp (chỉ dành cho học phần) / Nền tảng khóa học trực tuyến mở ví dụ: Udemy | AD22: AOV
A23: TRUE | B23: Em gửi hướng dẫn thanh toán và đăng ký học nhé ạ: https://drive.google.com/file/d/1rJtARzFiuHr0nCGtQjpMR3k9y6gLxu9H/view?usp=drive_link | C23: TELOS.vn | D23: TRUE | E23: 4 tuần | F23: Figma có những ưu điểm vượt trội photoshop trong việc thiết kế UI. 1. Rút ngắn thời gian trao đổi feedback & tracking khi nhiều thành viên có thể làm chung trong một project. Requester làm wireframe và designer thiết kế & dev trên cùng giao diện. 2. (Chế độ dev mod) Dev có thể copy paste nhanh được mã màu font chữ size chữ khoảng cách lề... -Designer khi làm xong có thể check được luôn CSS trông như nào (thông số màu/chữ/bố cục có lệch so với thiết kế không) từ đó trực tiếp chỉnh lại mà không cần phải chờ tới feedback của FE dev sau khi làm xong. 3.Plugin - Anima giúp export file thiết kế thành CSS do máy làm. Dev có thể tận dụng 1 phần code được viết sẵn - Anima có thể export tất cả các file ảnh trong thiết kế thành file png/ jpg dev đỡ phải cắt từng tấm ảnh thủ công - Remove background giúp tách background nhanh lẹ - Batch Styler giúp tạo style guideline nhanh lẹ có thể thay đổi màu sắc và font chữ hàng loạt thay vì chọn từng layer thủ công | H23: 45499 | I23: 4.400.000 VND (đã bao gồm VAT) | J23: 100% - tương ứng 4.400.000 VNĐ | K23: 2 buổi/tuần | L23: Khóa học FIGMA dành cho Designer/Developer | M23: Nhân viên tự trả tiền trước và claim theo mã dự án training | N23: Nắm vững và sử dụng thành thạo figma ứng dụng vào công việc thiết kế UI sự kiện ingame và UI cũng như các website phục vụ cho mục đích truyền thông của team. | O23: 45474 | P23: Hạng mục cấp thiết - tối đa 17 triệu VND / nội dung | Q23: https://telos.vn/khoa-hoc-thiet-ke-giao-dien-voi-figma/ | R23: Chi tiết nhu cầu của nhân sự đề xuất | S23: Chi tiết đề xuất từ bộ phận Đào tạo (dựa trên chính sách Hỗ trợ chi phí Đào tạo của Công ty) | T23: maithanh.le@garena.vn | U23: Đăng ký Hỗ trợ chi phí Đào tạo | V23: 43524 | W23: 45531 | X23: maithanh.le@garena.vn | Y23: 45464 | Z23: BP Đào tạo đề xuất | AA23: closed | AB23: Cấp thiết: Trực tiếp nâng cao kỹ năng và kiến thức trong lĩnh vực chuyên môn của nhân viên | AC23: Loại A: Các khóa học cấp chứng chỉ / Hội thảo / Hội nghị / Văn bằng hoặc Bằng cấp (chỉ dành cho học phần) / Nền tảng khóa học trực tuyến mở ví dụ: Udemy | AD23: AOV
A24: TRUE | B24: Em gửi hướng dẫn thanh toán và đăng ký học nhé ạ: https://drive.google.com/file/d/1Iry4EzFyDyAL6nkdBdMyv5Ej6VPWd-hn/view?usp=drive_link | C24: TELOS.vn | D24: TRUE | E24: 4 tuần | F24: • Nâng cao kỹ năng thiết kế UI/UX: Tạo giao diện đẹp trực quan thu hút users. • Tăng hiệu quả làm việc: Tự động hóa tối ưu hóa quy trình thiết kế tiết kiệm thời gian. • Giao tiếp cộng tác tốt hơn: Làm việc nhóm hiệu quả chia sẻ ý tưởng dễ dàng. • Phát triển tư duy sáng tạo: Thử nghiệm ý tưởng mới tạo trải nghiệm esports độc đáo. | H24: 45499 | I24: 4.400.000 VNĐ (đã bao gồm VAT) | J24: 100% - tương ứng 4.400.000 VNĐ | K24: 2 buổi 1 tuần | L24: Khoá học FIGMA DÀNH CHO DESIGNER/ DEVELOPER | M24: Nhân viên tự trả tiền trước và claim theo mã dự án training | N24: Mục tiêu khoá học: - Nắm vững và Sử dụng thành thạo figma - Ứng dụng figma vào công việc thiết kế UI | O24: 45474 | P24: Hạng mục cấp thiết - tối đa 17 triệu VND / nội dung | Q24: https://telos.vn/khoa-hoc-thiet-ke-giao-dien-voi-figma/ | R24: Chi tiết nhu cầu của nhân sự đề xuất | S24: Chi tiết đề xuất từ bộ phận Đào tạo (dựa trên chính sách Hỗ trợ chi phí Đào tạo của Công ty) | T24: hainguyen.dao@garena.vn | U24: Đăng ký Hỗ trợ chi phí Đào tạo | V24: 43527 | W24: 45531 | X24: hainguyen.dao@garena.vn | Y24: 45464 | Z24: BP Đào tạo đề xuất | AA24: closed | AB24: Cấp thiết: Trực tiếp nâng cao kỹ năng và kiến thức trong lĩnh vực chuyên môn của nhân viên | AC24: Loại A: Các khóa học cấp chứng chỉ / Hội thảo / Hội nghị / Văn bằng hoặc Bằng cấp (chỉ dành cho học phần) / Nền tảng khóa học trực tuyến mở ví dụ: Udemy | AD24: AOV
A25: TRUE | B25: withdraw điểu chỉnh lại nội dung,Em gửi kết quả phê duyệt và hướng dẫn đăng ký học & thanh toán cho anh Đông nhé ạ: https://drive.google.com/file/d/1ZpNDQNE4fuIAcC6ND32gsmfNFsooZvK8/view,Case study về tính hiệu quả của khóa học: Headsets bình luận viên: hiện tại studio có 9 headsets dùng cho bình luận các trận đấu và có khá nhiều loại khác nhau, trước kia việc mua các headsets này là dựa vào kinh nghiệm + trải nghiệm. Tuy nhiên sau khóa học đã hiểu rõ hơn về tính chất hoạt động riêng của từng Micro đi kèm theo headset và chức năng của nó dùng để làm gì. Vì vậy sẽ quyết định câu chuyện sẽ dùng cho trường hợp nào để phát huy hết công năng và nhu cầu về âm thanh. Ví dụ: case làm sự kiện. Trước khóa học: dư headsets nào thì lấy ra làm event. Sau khóa học: Nên chọn Headsets có mirco hyperCardioid (Model: HMD), micro này bắt sóng phía trước bình luận viên 1 góc 90 độ và khả năng bắt sóng tạp âm giữa hai bên vai và phía trước ít hơn so với dòng cardioid (Model: HME bắt góc 120 độ ) vì vậy sẽ tái tạo âm thanh được tốt hơn. | C25: Pro sound Academy | D25: TRUE | E25: 12 buổi (1 buổi tương đương 3 giờ học) | F25: Vận hành hệ thống âm thanh cho các giải đấu big offline bên ngoài chất lượng hơn mạng lại trải nghiệm tốt hơn cho người xem livestream. | H25: 45525 | I25: 8.500.000 VNĐ chưa bao gồm 8% VAT | J25: 100% - tương ứng 9 180 000 (đã bao gồm 8% VAT) | L25: Trọn bộ khóa học đào tạo âm thanh chuyên sâu (ứng dụng streaming và event) | M25: Nhân viên tự trả tiền trước và claim theo mã dự án training | N25: Bổ sung kiến thức nâng cao và đào sâu hơn kỹ năng chuyên môn về lĩnh vực Âm thanh. Qua đó có thể giúp ích khâu huấn luyện đào tạo chuyên sâu các kỹ năng cơ bản cho các bạn đang làm việc tại Studio xa hơn là huấn luyện cho các bạn cộng tác viên mới đủ để hiểu đúng và đủ rộng ứng dụng vào công việc một cách khoa học. Thông qua khóa học có thể kết hợp được kiến thức thực tiễn trải nghiệm đã từng trải + bổ trợ mới từ khóa học giúp đưa ra các nhận định đúng nhanh và quyết đoán hơn. Giảm thời gian xử ký các vấn đề liên quan đến âm thanh livestream bên ngoài các sự kiện do Công ty tổ chức. | O25: 45516 | P25: Hạng mục cấp thiết - tối đa 17 triệu VND / nội dung | Q25: https://www.facebook.com/people/Vietnam-Prosound-Academy/100063690095130/ | R25: Chi tiết nhu cầu của nhân sự đề xuất | S25: Chi tiết đề xuất từ bộ phận Đào tạo (dựa trên chính sách Hỗ trợ chi phí Đào tạo của Công ty) | T25: hodong.huynh@garena.vn | U25: Đăng ký Hỗ trợ chi phí Đào tạo | V25: 44054 | W25: 45530 | X25: hodong.huynh@garena.vn | Y25: 45492 | Z25: BP Đào tạo đề xuất | AA25: processing | AB25: Cấp thiết: Trực tiếp nâng cao kỹ năng và kiến thức trong lĩnh vực chuyên môn của nhân viên | AC25: Loại A: Các khóa học cấp chứng chỉ / Hội thảo / Hội nghị / Văn bằng hoặc Bằng cấp (chỉ dành cho học phần) / Nền tảng khóa học trực tuyến mở ví dụ: Udemy | AD25: STUDIO
A26: TRUE | B26: Em gửi kết quả phê duyệt, hướng dẫn đăng ký học và lộ trình học tập cho anh Hoạt nhé ạ - Kết quẳ phê duyệt & hướng dẫn đăng ký học: https://drive.google.com/file/d/1ZVXw3mmcZY4u97vXJk26AMhxQHcDR1n5/view?usp=drive_link - Lộ trình học tập: https://docs.google.com/document/d/1bX82Wup4zKpd7V66dqHq4j33R27gZX1J/edit?usp=drive_link&ouid=106903727602178885851&rtpof=true&sd=true | C26: Aroma | D26: TRUE | E26: 26 | F26: Trao đổi với đối tác nước ngoài tốt hơn phục vụ công việc trao đổi thông tin giao tiếp và trao đổi được với đối tác nước ngoài - Specific (Cụ thể) : Thành thạo tiếng Anh có thể giao tiếp được với các đồng nghiệp nước ngoài hoặc thuyết trình ý tưởng với các team global bằng tiếng Anh | H26: 45626 | I26: 8265000 | J26: 50% - tương ứng 4.132.500 VNĐ | K26: 20h30 – 22h00 T3 & T5 hàng tuần | L26: Khóa học nâng cao trình độ tiếng anh | M26: Nhân viên tự trả tiền trước và claim theo mã dự án training | N26: - Measurable : Đạt mục tiêu giao tiếp bằng tiếng anh với đối tác thông qua các buổi họp trình bày được các ý tưởng với đồng nghiệp và team nước ngoài - Actionable : làm và tạo các nội dung để chia sẻ trong team và các vùng khác - Relevant : Tăng cường thêm ngoại ngữ giúp đẩy nhanh hiệu quả công việc và độ chính xác cao hơn - Time-Bound: 6 tháng | O26: 45503 | P26: Hạng mục bổ trợ - tối đa 8.5 triệu VND / nội dung | Q26: http://aroma.vn/tieng-anh-cho-nguoi-di-lam/ | R26: Chi tiết nhu cầu của nhân sự đề xuất | S26: Chi tiết đề xuất từ bộ phận Đào tạo (dựa trên chính sách Hỗ trợ chi phí Đào tạo của Công ty) | T26: quanghoat.nguyen@garena.vn | U26: Đăng ký Hỗ trợ chi phí Đào tạo | V26: 44178 | W26: 45499 | X26: quanghoat.nguyen@garena.vn | Y26: 45498 | Z26: BP Đào tạo đề xuất | AA26: processing | AB26: Bổ trợ: Bổ trợ cho các kỹ năng và kiến thức trong lĩnh vực chuyên môn của nhân viên | AC26: Loại A: Các khóa học cấp chứng chỉ / Hội thảo / Hội nghị / Văn bằng hoặc Bằng cấp (chỉ dành cho học phần) / Nền tảng khóa học trực tuyến mở ví dụ: Udemy | AD26: FF
A27: TRUE | B27: Em gửi kết quả phê duyệt, hướng dẫn đăng ký học và lộ trình học tập cho anh Thao nhé ạ - Kết quẳ phê duyệt & hướng dẫn đăng ký học: https://drive.google.com/file/d/1ZUHZcGpu8If47vJf656XP3LYQV-y6tcw/view?usp=drive_link - Lộ trình học tập: https://docs.google.com/document/d/1dwMgOvwMjiOFqcxrrvsbg92jzyzp-Eiw/edit?usp=drive_link&ouid=106903727602178885851&rtpof=true&sd=true | C27: Aroma | D27: TRUE | E27: 5 tháng | F27: Thi thoảng em sẽ cần phải làm việc với bên vùng nhưng do bị hạn chế về ngôn ngữ nên hầu như đều nhờ đồng nghiệp/sếp present giúp. Vậy nên em mong muốn bản thân cần phải thành thạo tiếng Anh có thể giao tiếp được với các đồng nghiệp nước ngoài hoặc thuyết trình ý tưởng với các team global bằng tiếng Anh | H27: 45656 | I27: 8 265 000 VNĐ | J27: 50% - tương ứng 4.132.500 VNĐ | K27: 20h30 – 22h00 T3 & T5 hàng tuần | L27: Aroma | M27: Nhân viên tự trả tiền trước và claim theo mã dự án training | N27: - Specific (Cụ thể) : Thành thạo tiếng Anh có thể giao tiếp được với các đồng nghiệp nước ngoài hoặc thuyết trình ý tưởng với các team global bằng tiếng Anh - Measurable (Có thể Đo lường được) : Thành công trình bày ý tưởng của mình với các đồng nghiệp nước ngoài từ các buổi họp global. - Actionable (Tính Khả thi) : Trình bày các phương án phát triển kênh quản lý KOLs tối ưu quy trình quản lý KOLs cho global team. - Relevant (Sự Liên quan) : Trao đổi kiến thức của bản thân với global team - Time-Bound (Thời hạn đạt được mục tiêu) : 6 tháng. | O27: 45503 | P27: Hạng mục bổ trợ - tối đa 8.5 triệu VND / nội dung | Q27: http://aroma.vn/tieng-anh-cho-nguoi-di-lam/ | R27: Chi tiết nhu cầu của nhân sự đề xuất | S27: Chi tiết đề xuất từ bộ phận Đào tạo (dựa trên chính sách Hỗ trợ chi phí Đào tạo của Công ty) | T27: ducthao.tran@garena.vn | U27: Đăng ký Hỗ trợ chi phí Đào tạo | V27: 44179 | W27: 45499 | X27: ducthao.tran@garena.vn | Y27: 45498 | Z27: BP Đào tạo đề xuất | AA27: processing | AB27: Bổ trợ: Bổ trợ cho các kỹ năng và kiến thức trong lĩnh vực chuyên môn của nhân viên | AC27: Loại A: Các khóa học cấp chứng chỉ / Hội thảo / Hội nghị / Văn bằng hoặc Bằng cấp (chỉ dành cho học phần) / Nền tảng khóa học trực tuyến mở ví dụ: Udemy | AD27: FF
A28: TRUE | B28: Em gửi ý kiến của anh Minghao Xie, quản lý trực tiếp của team Infra VN về khóa học của Lê Khánh Nam nhé ạ. Nhờ anh Công review và approve giúp em nhé. Em cảm ơn ạ.,Em gửi hướng dẫn đăng ký và thanh toán cho anh Nam nhé ạ: https://drive.google.com/open?id=1_Lr6j_LfpfCRACt1sPJuoPxp0oVfAcuD&usp=drive_fs | C28: Cisco | D28: TRUE | E28: 8h | F28: 1. Nâng cao kiến thức kỹ năng thiết kế triển khai: Các dự án như mở rộng Freefire tại IDC VTHL mở rộng cụm Shopeepay 100G build up IDC mới tại Hòa Lạc cần triển khai một số mô hình mới và một số dòng thiết bị mới cần am hiểu thiết kế mô hình Enterprise/Data center để triển khai trong thời gian ngắn. 2. Nâng cao kinh nghiệm vận hành và xử lý sự cố đảm bảo chất lượng dịch vụ tới khách hàng: Chứng chỉ CCIE yêu cầu kỹ năng troubleshooting ở level expert nhằm đáp ứng SLA khắc phục sự cố trong thời gian ngắn đảm bảo chất lượng dịch vụ điều này mang ý nghĩa rất lớn khi áp dụng vào công việc để cho khách hàng trải nghiệm tốt nhất. 3. Nâng cao khả năng học hỏi trong công việc: Việc đạt được chứng chỉ này là tiền đề để hướng tới các chứng chỉ Expert level khác như CCIE Data center Devnet Security... từ đó ứng dụng được vào tất cả các mặt của công việc Network Engineer tối ưu hạ tầng giảm thiểu chi phí vận hành bằng các công nghệ mới tối ưu năng suất làm việc. | H28: 45532 | I28: 1600 USD | J28: 100% - tương ứng 17.000.000 VNĐ | L28: Thi chứng chỉ CCIE Enterprise Infrastructure | M28: Nhân viên tự trả tiền trước và claim theo mã dự án training | N28: Bổ sung kiến thức nâng cao trình độ lên level Expert trong networking | O28: 45532 | P28: Hạng mục cấp thiết - tối đa 17 triệu VND / nội dung | Q28: https://learningnetwork.cisco.com/s/ccie-enterprise | R28: Chi tiết nhu cầu của nhân sự đề xuất | S28: Chi tiết đề xuất từ bộ phận Đào tạo (dựa trên chính sách Hỗ trợ chi phí Đào tạo của Công ty) | T28: khanhnam.le@sea.com | U28: Đăng ký Hỗ trợ chi phí Đào tạo | V28: 44203 | W28: 45516 | X28: khanhnam.le@sea.com | Y28: 45499 | Z28: BP Đào tạo đề xuất | AA28: processing | AB28: Cấp thiết: Trực tiếp nâng cao kỹ năng và kiến thức trong lĩnh vực chuyên môn của nhân viên | AC28: Loại A: Các khóa học cấp chứng chỉ / Hội thảo / Hội nghị / Văn bằng hoặc Bằng cấp (chỉ dành cho học phần) / Nền tảng khóa học trực tuyến mở ví dụ: Udemy | AD28: SA_INFRA
A29: TRUE | C29: Wall Street English | D29: TRUE | E29: 3 tháng | F29: Giao tiếp tiếng Anh tốt hơn giúp giảm thời gian giao tiếp trao đổi trong các dự án tăng hiệu suất làm việc với các khu vực | H29: 45615 | I29: 9785000 | L29: Khóa học Tiếng Anh Wall Street English | N29: Hoàn thành khóa học trong 2 tháng ứng dụng nâng cao được vào công việc | O29: 45523 | Q29: https://wallstreetenglish.edu.vn/khoa-hoc-tieng-anh/nguoi-di-lam?utm_term=Lead&utm_campaign=WSEVN_NW_NonBranded_ProductFits_Lead_Google&utm_source=ppc&utm_medium=Google&hsa_acc=2735763208&hsa_cam=18173127804&hsa_grp=147383282544&hsa_ad=618917380235&hsa_src=g&hsa_tgt=dsa-1732094963205&hsa_kw=&hsa_mt=&hsa_net=adwords&hsa_ver=3&gad_source=1&gclid=CjwKCAjwyo60BhBiEiwAHmVLJSuoF-yun3N3pLxdadAjvPpORwDKBIjWIpDvSZWFAIoqkkq8gDgiFBoCObIQAvD_BwE | T29: hongduc.dao@garena.vn | U29: Đăng ký Hỗ trợ chi phí Đào tạo | V29: 44435 | W29: 45513 | X29: hongduc.dao@garena.vn | Y29: 45513 | AA29: closed | AB29: Bổ trợ: Bổ trợ cho các kỹ năng và kiến thức trong lĩnh vực chuyên môn của nhân viên | AC29: Loại A: Các khóa học cấp chứng chỉ / Hội thảo / Hội nghị / Văn bằng hoặc Bằng cấp (chỉ dành cho học phần) / Nền tảng khóa học trực tuyến mở ví dụ: Udemy | AD29: FF
A30: TRUE | B30: Em gửi link lộ trình khóa học của anh Đào Hồng Đức ạ: https://docs.google.com/document/d/1_4zWo3MFIiD8GJ8jgppyyNIBNg2Ax0Az/edit?usp=sharing&ouid=106903727602178885851&rtpof=true&sd=true ,Em gửi hướng dẫn đăng ký và thanh toán khóa học nhé ạ: https://drive.google.com/file/d/1_Zq4-laNlPTKrxioAIuNE_6bFXi7gKes/view?usp=drive_link | C30: Wall Street English | D30: TRUE | E30: 6 tháng | F30: #NAME? | H30: 45707 | I30: 19.570.000 VNĐ | J30: 50% - tương ứng 9.785.000 VNĐ | L30: Khóa học Tiếng Anh Wall Street English (Level 7) | M30: Nhân viên tự trả tiền trước và claim theo mã dự án training | N30: Sau 6 tháng đi từ Level 7 -> Level 8 theo khung của trung tâm - Thành thạo tiếng anh có thể giao tiếp được với các đồng nghiệp nước ngoài- Trình bày được các nội dung với các đồng nghiệp nước ngoài từ các buổi họp- Trình bày được các phương án giúp cho việc liên quan tới quy trình vận hành giải server giải | O30: 45523 | P30: Hạng mục bổ trợ - tối đa 8.5 triệu VND / nội dung | Q30: https://wallstreetenglish.edu.vn/khoa-hoc-tieng-anh/nguoi-di-lam?utm_term=Lead&utm_campaign=WSEVN_NW_NonBranded_ProductFits_Lead_Google&utm_source=ppc&utm_medium=Google&hsa_acc=2735763208&hsa_cam=18173127804&hsa_grp=147383282544&hsa_ad=618917380235&hsa_src=g&hsa_tgt=dsa-1732094963205&hsa_kw=&hsa_mt=&hsa_net=adwords&hsa_ver=3&gad_source=1&gclid=CjwKCAjwyo60BhBiEiwAHmVLJSuoF-yun3N3pLxdadAjvPpORwDKBIjWIpDvSZWFAIoqkkq8gDgiFBoCObIQAvD_BwE | R30: Chi tiết nhu cầu của nhân sự đề xuất | S30: Chi tiết đề xuất từ bộ phận Đào tạo (dựa trên chính sách Hỗ trợ chi phí Đào tạo của Công ty) | T30: hongduc.dao@garena.vn | U30: Đăng ký Hỗ trợ chi phí Đào tạo | V30: 44438 | W30: 45520 | X30: hongduc.dao@garena.vn | Y30: 45513 | Z30: Bổ sung thông tin | AA30: processing | AB30: Bổ trợ: Bổ trợ cho các kỹ năng và kiến thức trong lĩnh vực chuyên môn của nhân viên | AC30: Loại A: Các khóa học cấp chứng chỉ / Hội thảo / Hội nghị / Văn bằng hoặc Bằng cấp (chỉ dành cho học phần) / Nền tảng khóa học trực tuyến mở ví dụ: Udemy | AD30: FF
A31: TRUE | B31: Em gửi link lộ trình khóa học của anh Dương Đức ạ: https://docs.google.com/document/d/1_A1Dv_VhIsB-5wmsH8TAdzaabf6SOhsT/edit#heading=h.gjdgxs,Em gửi hướng dẫn đăng ký và thanh toán khóa học nhé ạ: https://drive.google.com/file/d/1_boXRnb6c--4R9BtLrA5oj3k-AlyiFsc/view?usp=drive_link | C31: Wall Street English | D31: TRUE | E31: 6 tháng | F31: Tăng được hiệu quả trong quá trình trao đổi thông tin rõ ràng hơn về việc tiếp nhận chia sẻ ý tưởng đến với những khu vực khác. | H31: 45707 | I31: 19.570.000 VNĐ (9.785.000 VNĐ/level) | J31: 50% - tương ứng 4.892.500 VND / level (nội dung) - Tổng cộng 2 level (nội dung): 9.785.000 VNĐ | L31: Khóa học Tiếng Anh Wall Street English (level 4 & 5) | M31: Nhân viên tự trả tiền trước và claim theo mã dự án training khi hoàn thành theo từng level (nội dung) | N31: Sau 6 tháng từ level 4 lên level 5. Mục tiêu học xong: trao đổi thông tin với các đồng nghiệp bên vùng / trình bày và thống nhất được các phương án / đề xuất ý tưởng cũng như thảo luận về các chủ đề xoay quanh công việc chính. Công việc hiện tại cần giao tiếp với nhiều đồng nghiệp tại các khu vực khác nhau về nội dung công việc nên sẽ cần tiếng anh để thông suốt thông tin để không bị gián đoạn. Cần học và cải thiện thêm về mặt ngôn ngữ để nâng cao trình độ bản thân đạt được nhiều cơ hội công việc hơn trong tương lai. | O31: 45523 | P31: Hạng mục bổ trợ - tối đa 8.5 triệu VND / nội dung | Q31: https://wallstreetenglish.edu.vn/khoa-hoc-tieng-anh/nguoi-di-lam?utm_term=Lead&utm_campaign=WSEVN_NW_NonBranded_ProductFits_Lead_Google&utm_source=ppc&utm_medium=Google&hsa_acc=2735763208&hsa_cam=18173127804&hsa_grp=147383282544&hsa_ad=618917380235&hsa_src=g&hsa_tgt=dsa-1732094963205&hsa_kw=&hsa_mt=&hsa_net=adwords&hsa_ver=3&gad_source=1&gclid=CjwKCAjwyo60BhBiEiwAHmVLJSuoF-yun3N3pLxdadAjvPpORwDKBIjWIpDvSZWFAIoqkkq8gDgiFBoCObIQAvD_BwE | R31: Chi tiết nhu cầu nhân sự đề xuất | S31: Chi tiết đề xuất từ bộ phận Đào tạo (dựa trên chính sách Hỗ trợ chi phí Đào tạo của Công ty) | T31: minhduc.duong@garena.vn | U31: Đăng ký Hỗ trợ chi phí Đào tạo | V31: 44448 | W31: 45520 | X31: minhduc.duong@garena.vn | Y31: 45516 | Z31: BP Đào tạo đề xuất | AA31: processing | AB31: Cấp thiết: Trực tiếp nâng cao kỹ năng và kiến thức trong lĩnh vực chuyên môn của nhân viên | AC31: Loại A: Các khóa học cấp chứng chỉ / Hội thảo / Hội nghị / Văn bằng hoặc Bằng cấp (chỉ dành cho học phần) / Nền tảng khóa học trực tuyến mở ví dụ: Udemy | AD31: FF
A32: TRUE | B32: Em gửi lộ trình khóa học của anh Đức ạ: https://docs.google.com/document/d/1_7HNraQr5tu7b0F_SM-OU993Dw4_pR9D/edit#heading=h.gjdgxs,Em gửi hướng dẫn đăng ký và thanh toán khóa học nhé ạ: https://drive.google.com/file/d/1_a5A9QmjnqRVt2aw8e7TAsh7XUeKbOf1/view?usp=drive_link | C32: Wall Street English | D32: TRUE | E32: 6 tháng | F32: Công việc cần giao tiếp với các vùng khác trao đổi dễ dàng hơn trong các dự án qua đó giúp cải thiện hiệu suất công việc | H32: 45707 | I32: 19.570.000 VNĐ (9.785.000 VNĐ/level) | J32: 50% - tương ứng 4.892.500 VND / level (nội dung) - Tổng cộng 2 level (nội dung): 9.785.000 VNĐ | L32: Khóa học Tiếng Anh Wall Street English (level 2 & 3) | M32: Nhân viên tự trả tiền trước và claim theo mã dự án training khi hoàn thành theo từng level (nội dung) | N32: - Trong thời gian 6 tháng hoàn thành khóa học từ level 2 đến level 3. - Thành thạo tiếng anh để có thể giao tiếp với team ở các khu vực khác. Tham gia các buổi họp 1 cách chủ động hơn để nắm bắt được các công việc và triển khai tốt nhất phục vụ cho công việc liên quan đến MKT Community. - Có thể chủ động raise các ý tưởng liên quan đến công việc mà không bị phụ thuộc vào công cụ phiên dịch | O32: 45523 | P32: Hạng mục bổ trợ - tối đa 8.5 triệu VND / nội dung | Q32: https://wallstreetenglish.edu.vn/khoa-hoc-tieng-anh/nguoi-di-lam?utm_term=Lead&utm_campaign=WSEVN_NW_NonBranded_ProductFits_Lead_Google&utm_source=ppc&utm_medium=Google&hsa_acc=2735763208&hsa_cam=18173127804&hsa_grp=147383282544&hsa_ad=618917380235&hsa_src=g&hsa_tgt=dsa-1732094963205&hsa_kw=&hsa_mt=&hsa_net=adwords&hsa_ver=3&gad_source=1&gclid=CjwKCAjwyo60BhBiEiwAHmVLJSuoF-yun3N3pLxdadAjvPpORwDKBIjWIpDvSZWFAIoqkkq8gDgiFBoCObIQAvD_BwE | R32: Chi tiết nhu cầu nhân sự đề xuất | S32: Chi tiết đề xuất từ bộ phận Đào tạo (dựa trên chính sách Hỗ trợ chi phí Đào tạo của Công ty) | T32: tienduc.nguyen@garena.vn | U32: Đăng ký Hỗ trợ chi phí Đào tạo | V32: 44449 | W32: 45520 | X32: tienduc.nguyen@garena.vn | Y32: 45516 | Z32: BP Đào tạo đề xuất | AA32: processing | AB32: Bổ trợ: Bổ trợ cho các kỹ năng và kiến thức trong lĩnh vực chuyên môn của nhân viên | AC32: Loại A: Các khóa học cấp chứng chỉ / Hội thảo / Hội nghị / Văn bằng hoặc Bằng cấp (chỉ dành cho học phần) / Nền tảng khóa học trực tuyến mở ví dụ: Udemy | AD32: FF
A33: TRUE | B33: Các khoá học trên INE rất chất lượng và chuyên sâu cho ngành IT. Các khoá học giúp bổ sung kiến thức chuyên ngành cho team Infra.,Em gửi hướng dẫn đăng ký học và thanh toán cho anh Cường nha ạ. | C33: INTERNETWORK EXPERT (INE) | D33: TRUE | E33: 3h53m | F33: - Nâng cao kiến thức kỹ năng thiết kế triển khai: Các dự án như mở rộng Freefire tại IDC VTHL mở rộng cụm Shopeepay 100G build up IDC mới tại Hòa Lạc cần triển khai một số mô hình mới và một số dòng thiết bị mới yêu cầu network engineer cần am hiểu thiết kế mô hình Enterprise/Data center để triển khai trong thời gian ngắn. Ngoài ra dự án moving IDC trong đầu năm 2025 yêu cầu hàm lượng chất xám cao trong việc thiết kế triển khai mô hình mới loại bỏ các thiết kế cũ đã lỗi thời.- Nâng cao kinh nghiệm vận hành và xử lý sự cố đảm bảo chất lượng dịch vụ tới khách hàng: Các khóa học expert level bổ sung kỹ năng troubleshooting cho cả Network và Dc Engineer nhằm đáp ứng SLA khắc phục sự cố trong thời gian ngắn đảm bảo chất lượng dịch vụ điều này mang ý nghĩa rất lớn khi áp dụng vào công việc để cho khách hàng trải nghiệm tốt nhất.- Bổ sung kiến thức về các công nghệ đang up trend: Các khóa học expert level về các lĩnh vực cyber security data science automation cloud bổ sung các kiến thức nền tảng và chuyên sâu nhằm đáp ứng các yêu cầu ngày càng nâng cao trong công việc: tăng cường bảo mật cho hệ thống tối ưu hóa work flow tự động hóa công việc hàng ngày nâng cao chất lượng hạ tầng đáp ứng các tiêu chuẩn kỹ thuật mới phục vụ security audit...- Nâng cao chất lượng nhân sự: Các khóa học trực tiếp hướng tới việc đạt được các chứng chỉ high và expert level trực tiếp nâng cao chất lượng nhân sự cho team SA-Infrastructure. | H33: 45565 | I33: 549 USD | J33: 100% - tương ứng 549 USD = 13.686.570 (theo tỉ giá Vietcombank ngày 05/09/2024) | L33: Khóa học Data Center ACI Concepts | M33: Nhân viên tự trả tiền trước và claim theo mã dự án training | N33: Bổ sung kiến thức nâng cao trình độ về Data Center | O33: 45540 | P33: Hạng mục cấp thiết - tối đa 17 triệu VNĐ / nội dung | Q33: ine.com | R33: Chi tiết nhu cầu nhân sự đề xuất | S33: Chi tiết đề xuất từ bộ phận Đào tạo (dựa trên chính sách Hỗ trợ chi phí Đào tạo của Công ty) | T33: huycuong.nguyen@sea.com | U33: Đăng ký Hỗ trợ chi phí Đào tạo | V33: 44793 | W33: 45568 | X33: huycuong.nguyen@sea.com | Y33: 45540 | Z33: Sửa thông tin khóa học | AA33: processing | AB33: Cấp thiết: Trực tiếp nâng cao kỹ năng và kiến thức trong lĩnh vực chuyên môn của nhân viên | AC33: Loại A: Các khóa học cấp chứng chỉ / Hội thảo / Hội nghị / Văn bằng hoặc Bằng cấp (chỉ dành cho học phần) / Nền tảng khóa học trực tuyến mở ví dụ: Udemy | AD33: SA_INFRA
A34: TRUE | B34: Em gửi hướng dẫn đăng ký học và thanh toán cho Phương nhé ạ | C34: Datapot | D34: TRUE | E34: 16 buổi - 32h | F34: Từ data có thể tự sửa lỗi mà không cần nhờ tới bộ phân khác trực tiếp lấy dữ liệu ứng biến kịp thời khi đọc data để đề bạt next step trong các campaign | H34: 45614 | I34: 6.264.000 VNĐ (đã bao gồm 8% VAT) | J34: 100% của khóa học - tương ứng 6.264.000 VNĐ (đã bao gồm 8% VAT) | K34: 2 buổi/tuần - thứ 2 và thứ 5 | L34: PowerBI Data Analytics Basic | M34: Nhân viên tự trả tiền trước và claim theo mã dự án training | N34: Học cách xử lý dữ liệu và phân tích collect lỗi có trong data sẵn có ứng dụng trực tiếp vào các campaign đang và sắp diễn ra | O34: 45572 | P34: Hạng mục cấp thiết - tối đa 17 triệu VND / nội dung | Q34: https://datapot.vn/khoa-hoc/da-100-analyzing-data-with-power-bi/ | R34: Chi tiết nhu cầu của nhân sự đề xuất | S34: Chi tiết đề xuất từ bộ phận Đào tạo (dựa trên chính sách Hỗ trợ chi phí Đào tạo của Công ty) | T34: maiphuong.pham@garena.vn | U34: Đăng ký Hỗ trợ chi phí Đào tạo | V34: 44973 | W34: 45567 | X34: maiphuong.pham@garena.vn | Y34: 45553 | Z34: BP Đào tạo đề xuất | AA34: processing | AB34: Cấp thiết: Trực tiếp nâng cao kỹ năng và kiến thức trong lĩnh vực chuyên môn của nhân viên | AC34: Loại A: Các khóa học cấp chứng chỉ / Hội thảo / Hội nghị / Văn bằng hoặc Bằng cấp (chỉ dành cho học phần) / Nền tảng khóa học trực tuyến mở ví dụ: Udemy | AD34: FF
A35: TRUE | B35: Em gửi hướng dẫn đăng ký học và thanh toán cho chị Linh nhé ạ. | C35: Datapot | D35: TRUE | E35: 32 giờ | F35: Từ data có thể phân tích sâu hơn để tìm ra những giải pháp tối ưu trong việc tăng trưởng doanh thu | H35: 45624 | I35: 6.264.000 VNĐ (đã bao gồm 8% VAT) | J35: 100% của khóa học - tương ứng 6.264.000 VNĐ (bao gồm VAT 8%) | K35: 2 buổi / tuần | L35: PowerBI Data Analytics Basic | M35: Nhân viên tự trả tiền trước và claim theo mã dự án training | N35: #NAME? | O35: 45483 | P35: Hạng mục cấp thiết - tối đa 17 triệu VND / nội dung | Q35: https://datapot.vn/khoa-hoc/da-100-analyzing-data-with-power-bi/ | R35: Chi tiết nhu cầu của nhân sự đề xuất | S35: Chi tiết đề xuất từ bộ phận Đào tạo (dựa trên chính sách Hỗ trợ chi phí Đào tạo của Công ty) | T35: mylinh.pham@garena.vn | U35: Đăng ký Hỗ trợ chi phí Đào tạo | V35: 44974 | W35: 45567 | X35: mylinh.pham@garena.vn | Y35: 45553 | Z35: BP Đào tạo đề xuất | AA35: processing | AB35: Cấp thiết: Trực tiếp nâng cao kỹ năng và kiến thức trong lĩnh vực chuyên môn của nhân viên | AC35: Loại A: Các khóa học cấp chứng chỉ / Hội thảo / Hội nghị / Văn bằng hoặc Bằng cấp (chỉ dành cho học phần) / Nền tảng khóa học trực tuyến mở ví dụ: Udemy | AD35: FF
A36: TRUE | B36: Approved,Em gửi anh Thắng hướng dẫn đăng ký học và thanh toán nhé ạ | C36: CÔNG TY TNHH GIẢI PHÁP VÀ CHUYỂN GIAO CÔNG NGHỆ PNH | D36: TRUE | E36: 64h | F36: Khi một **network engineer** trong công ty học **DevOps** họ có thể mang lại nhiều lợi ích cho doanh nghiệp. Dưới đây là 5 điểm chính: 1. **Tối ưu hóa hiệu suất vận hành mạng**: Với DevOps network engineers có thể tự động hóa các tác vụ mạng giảm thiểu lỗi thủ công từ đó giúp hệ thống vận hành trơn tru và ổn định hơn giảm thời gian downtime. 2. **Rút ngắn thời gian triển khai hạ tầng**: Sử dụng mô hình Infrastructure as Code (IaC) giúp việc triển khai và cấu hình mạng nhanh chóng và có thể lặp lại dễ dàng từ đó đẩy nhanh tốc độ triển khai dự án và dịch vụ. 3. **Cải thiện sự phối hợp giữa các bộ phận**: DevOps khuyến khích sự cộng tác chặt chẽ giữa các nhóm phát triển vận hành và mạng giúp giải quyết vấn đề nhanh chóng và nâng cao hiệu quả công việc đặc biệt trong các dự án lớn. 4. **Tăng cường bảo mật và giám sát mạng**: Network engineers có thể sử dụng các công cụ DevOps để giám sát hệ thống theo thời gian thực và phát hiện xử lý sớm các rủi ro bảo mật từ đó bảo vệ hạ tầng mạng của công ty. 5. **Tối ưu hóa chi phí hạ tầng**: Tự động hóa và quản lý tài nguyên thông qua DevOps giúp công ty tiết kiệm chi phí bằng cách giảm nhu cầu về nhân lực quản lý sử dụng tài nguyên hiệu quả hơn và tránh lãng phí do sai sót trong cấu hình. Những lợi ích này giúp công ty hoạt động hiệu quả hơn an toàn hơn và tiết kiệm thời gian chi phí trong dài hạn. | H36: 45662 | I36: 10500000 | J36: 100% - tương ứng 10.500.000 VNĐ | K36: 20-22h Thứ 3 5 7 hàng tuần | L36: KHÓA HỌC DEVOPS PRO | M36: Nhân viên tự trả tiền trước và claim theo mã dự án training | N36: - Tự động hóa cấu hình mạng: Network engineers sẽ hiểu và sử dụng các công cụ như Ansible Terraform để tự động hóa quá trình cấu hình và quản lý hạ tầng mạng giúp giảm sai sót và tăng hiệu suất công việc. - Quản lý hệ thống hạ tầng mạng linh hoạt: DevOps giúp network engineers xây dựng hạ tầng mạng theo mô hình Infrastructure as Code (IaC) giúp dễ dàng triển khai cấu hình và mở rộng mạng nhanh chóng. - Tích hợp CI/CD cho quản lý mạng: Với DevOps network engineers có thể tích hợp quy trình Continuous Integration/Continuous Deployment (CI/CD) để tự động kiểm thử và triển khai các thay đổi về mạng tăng tính ổn định và hiệu quả. - Giám sát và quản lý sự cố hiệu quả hơn: DevOps trang bị kỹ năng sử dụng các công cụ giám sát (như Prometheus Grafana ELK Stack) giúp network engineers có khả năng phát hiện xử lý sự cố nhanh chóng và chính xác hơn. - Tư duy phát triển và vận hành đồng bộ: Khi học DevOps network engineers hiểu sâu hơn về sự liên kết giữa phát triển phần mềm và hạ tầng mạng giúp cải thiện quá trình phối hợp giữa các đội ngũ phát triển và vận hành trong doanh nghiệp. | O36: 45570 | P36: Hạng mục cấp thiết - tối đa 17 triệu VNĐ / nội dung | Q36: https://pnh.vn/khoa-hoc-devops-pro/ | R36: Chi tiết nhu cầu nhân sự đề xuất | S36: Chi tiết đề xuất từ bộ phận Đào tạo (dựa trên chính sách Hỗ trợ chi phí Đào tạo của Công ty) | T36: vietthang.dinh@garena.vn | U36: Đăng ký Hỗ trợ chi phí Đào tạo | V36: 45112 | W36: 45568 | X36: vietthang.dinh@garena.vn | Y36: 45562 | Z36: BP Đào tạo đề xuất | AA36: processing | AB36: Cấp thiết: Trực tiếp nâng cao kỹ năng và kiến thức trong lĩnh vực chuyên môn của nhân viên | AC36: Loại A: Các khóa học cấp chứng chỉ / Hội thảo / Hội nghị / Văn bằng hoặc Bằng cấp (chỉ dành cho học phần) / Nền tảng khóa học trực tuyến mở ví dụ: Udemy | AD36: SA_IT
A37: TRUE | B37: Em gửi hướng dẫn đăng ký học và thanh toán cho anh Thế Anh nhé ạ. | C37: Datapot | D37: TRUE | E37: 16 buổi - 32 tiếng | F37: Từ data có thể phân tích sâu hơn để tìm ra những giải pháp tối ưu trong việc tăng trưởng user | H37: 45614 | I37: 6.264.000 VNĐ (đã bao gồm 8% VAT) | J37: 100% của khóa học - tương ứng 6.264.000 VNĐ (bao gồm VAT 8%) | L37: PowerBI Data Analytics Basic | M37: Nhân viên tự trả tiền trước và claim theo mã dự án training | N37: Xử lý dữ liệu để đưa ra quyết định phù hợp với định hướng của sản phẩm và công ty | O37: 45572 | P37: Hạng mục cấp thiết - tối đa 17 triệu VND / nội dung | Q37: https://datapot.vn/khoa-hoc/da-100-analyzing-data-with-power-bi/ | R37: Chi tiết nhu cầu của nhân sự đề xuất | S37: Chi tiết đề xuất từ bộ phận Đào tạo (dựa trên chính sách Hỗ trợ chi phí Đào tạo của Công ty) | T37: theanh.nguyennhu@garena.vn | U37: Đăng ký Hỗ trợ chi phí Đào tạo | V37: 45128 | W37: 45567 | X37: theanh.nguyennhu@garena.vn | Y37: 45565 | Z37: BP Đào tạo đề xuất | AA37: processing | AB37: Cấp thiết: Trực tiếp nâng cao kỹ năng và kiến thức trong lĩnh vực chuyên môn của nhân viên | AC37: Loại A: Các khóa học cấp chứng chỉ / Hội thảo / Hội nghị / Văn bằng hoặc Bằng cấp (chỉ dành cho học phần) / Nền tảng khóa học trực tuyến mở ví dụ: Udemy | AD37: FF
A38: TRUE | C38: CÔNG TY TNHH GIẢI PHÁP VÀ CHUYỂN GIAO CÔNG NGHỆ PNH | D38: TRUE | E38: Chiều thứ 7 hàng tuần 1h30 - 5h30 | F38: Vận hành hệ thống CNTT nâng cao bảo mật hệ thống | H38: 45703 | I38: 15 triệu | L38: Khóa học CISSP | N38: Nâng cao nhận thức và các tiêu chuẩn bảo mật của ngành CNTT | O38: 45580 | Q38: https://pnh.vn/khoa-hoc-cissp/ | T38: khanhhoang.tran1@garena.vn | U38: Đăng ký Hỗ trợ chi phí Đào tạo | V38: 45132 | W38: 45565 | X38: khanhhoang.tran1@garena.vn | Y38: 45565 | Z38: thay đổi ngày kết thúc khóa học | AA38: approving | AB38: Cấp thiết: Trực tiếp nâng cao kỹ năng và kiến thức trong lĩnh vực chuyên môn của nhân viên | AC38: Loại A: Các khóa học cấp chứng chỉ / Hội thảo / Hội nghị / Văn bằng hoặc Bằng cấp (chỉ dành cho học phần) / Nền tảng khóa học trực tuyến mở ví dụ: Udemy | AD38: SA_IT
A39: TRUE | C39: Tomorrow Marketer | D39: TRUE | E39: Test | F39: Test | H39: 45581 | I39: 5750000 | K39: Test | L39: Phân tích dữ liệu cho quyết định chiến lược | N39: Test | O39: 45574 | Q39: https://www.tomorrowmarketers.org/data-analysis-course | T39: garenahr@garena.vn | U39: Đăng ký Hỗ trợ chi phí Đào tạo | V39: 45141 | W39: 45566 | X39: garenahr@garena.vn | Y39: 45566 | AA39: approving | AB39: Cấp thiết: Trực tiếp nâng cao kỹ năng và kiến thức trong lĩnh vực chuyên môn của nhân viên | AC39: Loại A: Các khóa học cấp chứng chỉ / Hội thảo / Hội nghị / Văn bằng hoặc Bằng cấp (chỉ dành cho học phần) / Nền tảng khóa học trực tuyến mở ví dụ: Udemy | AD39: RECRUITMENT_AND_TRAINING

Sheet Feedback (Training Budget Spons
A1: Dấu thời gian | B1: Workshop | C1: Địa chỉ email | D1: Department/Team Phòng ban | E1: Đánh giá trải nghiệm của bạn [Trải nghiệm chung với toàn bộ dịch vụ đào tạo được cung cấp] | F1: Đánh giá trải nghiệm của bạn [Mức độ hài lòng với giải pháp / nội dung đào tạo] | G1: Đánh giá trải nghiệm của bạn [Mức độ hài lòng với giảng viên / đối tác / tổ chức cung cấp nội dung] | H1: Đánh giá trải nghiệm của bạn [Mức độ hài lòng với công tác tổ chức và hỗ trợ của Bộ phận Đào tạo?] | I1: Vui lòng chia sẻ một điều mà bạn học được và có thể áp dụng trong thực tế công việc sau dịch vụ đào tạo này? (Tùy chọn trả lời) | J1: Vui lòng chia sẻ thêm các phản hồi /gợi ý khác của bạn để cải thiện chất lượng đào tạo? Tùy chọn trả lời | K1: Topic feedback
A2: 45409 | B2: Xây dựng văn hóa doanh nghiệp và hệ thống truyền thông nội bộ | C2: linhtrang.tran@garena.vn | D2: PPS | E2: 5 | F2: 4 | G2: 5 | H2: 5 | I2: Khảo sát Văn hóa doanh nghiệp. | J2: Rất tốt rồi ạ.
A3: 45516.619 | B3: Phân tích dữ liệu cho quyết định chiến lược | C3: phuongthao.le@garena.vn | D3: FCO | E3: 3 | F3: 4 | G3: 3 | H3: 4 | I3: Khóa học cung cấp mindset về việc áp dụng Phân tích số liệu vào công việc. Từ vấn đề của doanh nghiệp, lập issue tree để xác định những loại dữ liệu cần thu thập, phân tích và đưa ra solution phù hợp. Khóa học cũng nhấn mạnh, số liệu phải được kết hợp với business insight để đưa ra solution phù hợp. Nếu chỉ dựa trên số liệu mà không kết hợp với business insight sẽ dễ dẫn đến nhận định và giải pháp không phù hợp. Cách sử dụng cơ bản Power BI trong việc xử lý dữ liệu và thực hiện báo cáo. Sau khóa học, có thể áp dụng việc thiết lập file collect report từ các dự án marketing, xử lý số liệu bằng power BI và thiết lập báo cáo, từ đó có thể đưa ra các giải pháp marketing dựa trên số liệu (kết hợp business insight). | J3: Lịch dạy của khóa đào tạo có 3 lần trainer báo bận đột xuất và lớp nghỉ, dẫn đến việc ảnh hưởng việc sắp xếp lịch học và làm việc của mình. . | K3: Trainer & đối tác
A4: 45530.685 | B4: Đào tạo âm thanh chuyên sâu | C4: hodong.huynh@garena.vn | D4: Studio | E4: 5 | F4: 5 | G4: 5 | H4: 5 | I4: Một vài điểm tâm đắc sau khóa học: 1. Kiến thức về Audio: - Chuẩn hóa kiến thức: Sau khi tham gia khóa học đãchuẩn hóa và nắm vững các kiến thức về thiết bị và quy cách vận hành một cách rõ ràng hơn. Không còn mơ hồ hoặc không hiểu là đúng hay là sai. - Hiểu quy tắc và nguyên lý: nắm được các quy tắc và nguyên lý hoạt động của các thiết bị Audio dùng trong phòng thu và hệ thống vận hành cho các sự kiện. Điều này giúp thiết lập mới hoặc tái thiết lập một cách hiệu quả hơn. - Tiếp thu kiến thức hệ thống chuyên nghiệp: học thêm về các hệ thống chuyên nghiệp dùng cho các sự kiện lớn, từ đó có thể tìm hiểu sâu hơn về nguyên nhân gốc rễ nếu có và tối ưu hóa chi phí cũng như trải nghiệm người nghe hơn. 2. Giải pháp thiết bị: Hiểu sâu về hoạt động thiết bị: nắm rõ cách thức hoạt động của mỗi thiết bị và biết cách áp dụng, triển khai phù hợp theo từng không gian và nhu cầu thực tế, qua đó giúp tối ưu chi phí và hiệu suất. case study: Headsets bình luận viên: hiện tại studio có 9 headsets dùng cho bình luận các trận đấu và có khá nhiều loại khác nhau, trước kia việc mua các headsets này là dựa vào kinh nghiệm + trải nghiệm. Tuy nhiên sau khóa học đã hiểu rõ hơn về tính chất hoạt động riêng của từng Micro đi kèm theo headset và chức năng của nó dùng để làm gì. Vì vậy sẽ quyết định câu chuyện sẽ dùng cho trường hợp nào để phát huy hết công năng và nhu cầu về âm thanh. Ví dụ: case làm sự kiện. Trước khóa học: dư headsets nào thì lấy ra làm event. Sau khóa học: Nên chọn Headsets có mirco hyperCardioid (Model: HMD), micro này bắt sóng phía trước bình luận viên 1 góc 90 độ và khả năng bắt sóng tạp âm giữa hai bên vai và phía trước ít hơn so với dòng cardioid (Model: HME bắt góc 120 độ ) vì vậy sẽ tái tạo âm thanh được tốt hơn.
A5: 45531.613 | B5: PowerBI | C5: quanghuy.duong@garena.vn | D5: 3KD | E5: 5 | F5: 5 | G5: 5 | H5: 5 | I5: Vốn dĩ khi làm 3KD vẫn dùng PBI hàng ngày nhưng sau khóa học đã hiểu tường tận hơn. | J5: Bản thân thấy khá may vì chọn được lớp ưng ý để đi học sớm. Do đó nếu ai có nhu cầu đi học thì nên chia sẻ sớm với HR team để tối ưu thời gian tốt nhất.
A6: 45531.613 | B6: Figma for Designer | C6: tienthanh.tran@garena.vn | D6: AOV | E6: 5 | F6: 5 | G6: 5 | H6: 5 | I6: hệ thống component giúp đẩy nhanh công việc thiết kế website..
A7: 45531.613 | B7: Figma for Designer | C7: maithanh.le@garena.vn | D7: AOV | E7: 5 | F7: 5 | G7: 5 | H7: 5 | I7: Tư duy hệ thống trong Figma đã giúp tôi cải thiện đáng kể trong thời gian hoàn thành sản phẩm (cụ thể là thiết kế trang web sự kiện dẫn từ Game)..
A8: 45531.613 | B8: Figma for Designer | C8: hainguyen.dao@garena.vn | D8: AOV | E8: 4 | F8: 4 | G8: 4 | H8: 4 | I8: Đã có thể sử dụng phần mềm Figma ở mức cơ bản, có thể ứng dụng cho việc thiết kế giao diện đúng quy chuẩn hơn về sau.
A9: 45565.634 | B9: Advanced Total Rewards Strategy | C9: vananh.le@garena.vn | D9: PPT | E9: 4 | F9: 4 | G9: 5 | H9: 5 | I9: Advanced Total Rewards có 1 số chart có thể áp dụng để đánh giá bottleneck cho Garena. Các mô hình trả lương thưởng đối với từng thời kỳ phát triển của một doanh nghiệp nên khác nhau, VD từ start up đến growth, maintaining và Shrinking nên có mô hình khác nhau.
A10: 45568.553 | B10: Khóa học Data Center ACI Concepts | C10: khanhnam.le@garena.vn | D10: Infra | E10: 5 | F10: 5 | G10: 5 | H10: 5 | I10: Khóa học này cung cấp các kiến thức bổ ích và cấp thiết để dần đưa công nghệ VXLAN EVPN và SDN vào triển khai trong Data center, tối ưu hóa công việc vận hành, đặc biệt cấp thiết trong việc triển khai dự án mở rộng cụm FreeFire tại VTHL IDC trong tháng 10 này. | J10: Nếu có thể hi vọng bộ phận đào tạo có thể tối ưu hóa quy trình phê duyệt nhanh gọn hơn nhé.
A11: 45614 | B11: PowerBI | C11: maiphuong.pham@garena.vn | D11: FF | E11: 3 | F11: 3 | G11: 3 | H11: 3 | I11: Đã lên được visualise report + viết code + input data cơ bản để lên được báo cáo về số liệu - tuy nhiên chưa lên được các data dẫn link hoặc lấy link do chưa học hoặc phần này liên quan đến advance . | J11: - Nhiều giáo viên hướng dẫn + lớp rất đông nên không xác định nổi là cần nhờ ai để giải đáp thắc mắc - Sửa bài tập về nhà thường chiếm 1 tiếng thậm chí hơn, lý thuyết học 30 phút sau đó làm bài tập và lố giờ tương đối nhiều.
A12: 45741 | B12: English Online Course (WSE) | C12: hongduc.dao@garena.vn | D12: FF | E12: 4 | F12: 4 | G12: 3 | H12: 4 | I12: - Sau khoá học cũng cải thiện hơn về kỹ năng nghe - Thêm tự tin hơn khi trao đổi công việc với các khu vực thông qua giải đấu tháng 2 vừa rồi..
A13: 45741 | B13: Digital Advanced: Digital Foundation & Digital Performance | C13: minhkhoi.nguyen@garena.vn | D13: FCO | E13: 4 | F13: 4 | G13: 5 | H13: 5 | I13: Hiểu được rõ ràng về tư duy Digital Marketing, cụ thể hơn là chạy OM. Hiểu hơn về thuật toán hoạt động ở 1 số nền tảng social khác để áp dụng vào việc chạy dự án về sau. | J13: Học online nên đôi lúc tương tác và khả năng tiếp thu không được hiệu quả cho lắm.
A14: 45741 | B14: Khóa học Báo cáo và Trình diễn dữ liệu thông minh | C14: minhngoc.phamnguyen@garena.vn | D14: PPT | E14: 5 | F14: 5 | G14: 5 | H14: 5
A15: 45923 | B15: PowerBI | C15: phuongthao.tran@garena.vn | D15: Ff | E15: 4 | F15: 4 | G15: 5 | H15: 4 | I15: Khóa học hữu ích trong việc xây dựng mindset phân tích dữ liệu và quy trình thực hiện tư duy phân tích. Học được cách đặt câu hỏi đúng trước khi bắt tay vào xây dựng dashboard. Biết cách suy nghĩ theo hướng "business-driven", nghĩa là mọi biểu đồ, chỉ số hiển thị đều phải phục vụ cho mục tiêu phân tích cụ thể. Các ví dụ trong khóa học rất gần gũi với thực tế doanh nghiệp. Mình có nền tảng Excel hoặc hiểu biết cơ bản về dữ liệu nên nội dung học khá thú vị và gây được sự hứng thú để tìm hiểu sâu hơn. .
A16: 45923 | B16: Tiếng Trung thầy Hưng 23b | C16: minhtri.hoang@garena.vn | D16: FF | E16: 5 | F16: 5 | G16: 5 | H16: 5 | I16: Tôi đã có tiến bộ rõ rệt trong việc đọc và nói tiếng Trung, tuy nhiên chưa đủ để apply luôn vào công việc hiện tại. Cần take thêm 1-2 courses nữa..
A17: 45923 | B17: Tiếng Trung thầy Hưng 23b | C17: mylinh.pham@garena.vn | D17: FF | E17: 5 | F17: 5 | G17: 5 | H17: 5 | I17: Giao tiếp với dev vùng hiệu quả hơn.

Sheet Feedback (Request)
A1: Timestamp | B1: Email Address | C1: Tên của bạn | D1: Nội dung đề xuất của bạn | E1: Đánh giá trải nghiệm của bạn [Trải nghiệm chung với toàn bộ dịch vụ đào tạo được cung cấp] | F1: Đánh giá trải nghiệm của bạn [Mức độ hài lòng với giải pháp / nội dung đào tạo] | G1: Đánh giá trải nghiệm của bạn [Mức độ hài lòng với giảng viên / đối tác / tổ chức cung cấp nội dung] | H1: Đánh giá trải nghiệm của bạn [Mức độ hài lòng với công tác tổ chức và hỗ trợ của Bộ phận Đào tạo (Garena)?] | I1: Vui lòng chia sẻ một điều mà bạn học được và có thể áp dụng trong thực tế công việc sau dịch vụ đào tạo này? | J1: Vui lòng chia sẻ thêm các phản hồi /gợi ý khác của bạn để cải thiện chất lượng đào tạo? Tùy chọn trả lời | K1: Gửi chứng chỉ hoàn thành khóa của bạn tại đây nhé! | L1: Đánh giá trải nghiệm của bạn [Row 5]
A2: 45463.769 | B2: vietanh.than@garena.vn | C2: Thân Việt Anh | D2: BA Course 1 | E2: 5 | F2: 3 | G2: 5 | H2: 5 | I2: - Tool: Figma - Doc: BRD, FDR, SRS - Framework quản lý dự án: Sprint, Agile | J2: Kì vọng hơn về việc cách viết site map, logic; các logic khi thiêt kế UI UX (đo bằng click,...etc). Nói chung khóa học provide framework ở mức cơ bản
A3: 45467.499 | B3: lenam.to@garena.vn | C3: Tô Lê Nam | D3: BA Course 1 | E3: 4 | F3: 4 | G3: 4 | H3: 4
A4: 45467.644 | B4: tienthanh.tran@garena.vn | C4: Trần Tiến Thành | D4: BA Course 1 | E4: 5 | F4: 5 | G4: 5 | H4: 5
A5: 45467.654 | B5: huyenanh.phan@garena.vn | C5: Huyền Anh | D5: BA Course 1 | E5: 5 | F5: 4 | G5: 4 | H5: 4 | I5: Bộ câu hỏi 5W 1H kèm các tài liệu giúp phân tích đề bài, hiểu nhu cầu của requester / bản thân rõ hơn | J5: Nếu BPĐT gom hết tài liệu vào 1 link drive cty rồi share lại cho lớp để lưu trữ thì toẹt vời ạ :D
A6: 45475.44 | B6: thienkhoa.le@garena.vn | C6: Lê Trần Thiện Khoa | D6: BA Course 1 | E6: 4 | F6: 4 | G6: 4 | H6: 4
A7: 45475.441 | B7: phuonglinh.pham@garena.vn | C7: Phạm Phương Linh | D7: BA Course 1 | E7: 4 | F7: 3 | G7: 4 | H7: 5
A8: 45475.441 | B8: viethop.nguyen@garena.vn | C8: Phưng | D8: BA Course 1 | E8: 4 | F8: 4 | G8: 4 | H8: 4 | I8: Scrum/Agile/Waterfall ==> Tuy more relate to dev nhưng nói chung xài được | J8: Chưa có
A9: 45475.444 | B9: minhkhoi.tran@garena.vn | C9: Trần Minh Khôi | D9: BA Course 1 | E9: 5 | F9: 4 | G9: 4 | H9: 5
A10: 45475.459 | B10: haison.tran@garena.vn | C10: Trần Trung Hải Sơn | D10: BA Course 1 | E10: 4 | F10: 4 | G10: 4 | H10: 4 | I10: Figma
A11: 45475.466 | B11: thaianh.tran@garena.vn | C11: Trần Thái Anh | D11: BA Course 1 | E11: 4 | F11: 4 | G11: 3 | H11: 4 | I11: Sử dụng Figma, cách phân chia lên plan task và đầu công việc
A12: 45475.503 | B12: anhvu.huynh@garena.vn | C12: Huỳnh Nguyễn Anh Vũ | D12: BA Course 1 | E12: 3 | F12: 2 | G12: 3 | H12: 3 | I12: Có thể làm tốt hơn trong các dự án sắp tới về mặt wireframe, sắp xếp tốt bố cục và tối ưu hóa giao diện
A13: 45475.583 | B13: traanh.au@garena.vn | C13: Trà Anh | D13: BA Course 1 | E13: 5 | F13: 5 | G13: 4 | H13: 5
A14: 45568.774 | B14: khaikien.duong@garena.vn | C14: Dương Khải Kiên | D14: BA Course 2 | E14: 4 | F14: 4 | G14: 4 | H14: 5 | I14: Thanks chị Nhân vì đã share rất nhiều kiến thức liên quan tới việc đánh giá một Business, trong đó có phần cảm thấy nhận được nhiều kiến thức nhất là phần liên quan đến Stakeholders. | J14: Công tác chuẩn bị của team Đào tạo rất tốt, nỗ lực sắp xếp thời gian để mọi staff có thể tham gia học được, đặc biệt là với team eSports FF phải đi công tác liên tục. Very appreciate!!!
A15: 45569.582 | B15: ngoclong.nguyen@garena.vn | C15: Nguyễn Ngọc Long | D15: BA Course 2 | E15: 4 | F15: 2 | G15: 3 | H15: 3 | J15: - Kiến thức ở khóa này hơi chung chung và chỉ dừng lại ở lý thuyết là chủ yếu (cái này em nghĩ là do em đặt kỳ vọng hơi cao trước khi học ạ :)) - Các kiến thức mà bọn em mong chờ nhất là figma thì lại được dạy hơi lộn xộn, mà em nghĩ lý do chính là vì anh thầy giáo dạy (anh này nói vừa nhỏ lại vừa run run, xong nói còn không theo thứ tự gì nên khó tiếp cận, em toàn phải hỏi lại) - Còn lại mọi thứ đều ổn ạ
A16: 45569.6 | B16: mylinh.pham@garena.vn | C16: Mỹ Linh | D16: BA Course 2 | E16: 1 | F16: 1 | G16: 1 | H16: 5 | J16: Giảng viên dạy lướt và các ví dụ đưa ra không thiết thực với công việc của mình lắm nên mình cảm thấy mình chỉ có thể nắm được lý thuyết cơ bản. Lý thuyết cô dạy cũng không khác gì tự đọc slide. Các ví dụ nên được customize lấy trực tiếp từ công việc thực tế của mình hiện tại, ví dụ như các web event team đã / đang làm. Cô đưa ra 1 số ví dụ ko liên quan như app CGV, không ai dùng và team không làm app bao giờ nên cảm thấy khó rút kinh nghiệm, áp dụng vào công việc. Nếu tập trung dạy lý thuyết thì có thể hướng dẫn mọi người học base trên Coursera trước
A17: 45569.6 | B17: quanghuy.duong@garena.vn | C17: Dương Quang Huy | D17: BA Course 2 | E17: 3 | F17: 2 | G17: 4 | H17: 3 | I17: Hiểu hơn 1 chút về drawio nên sử dụng nhiều hơn trong dự án H5 | J17: Lớp học này đang hơi bị động. Nếu có thể nên có bước tìm hiểu trước các nội dung của khóa học để có góc nhìn, sau đó đưa ra các vấn đề từ bản thân thực tế trong nội dung từng buổi học
A18: 45569.644 | B18: hongduc.dao@garena.vn | C18: Đào Hồng Đức | D18: BA Course 2 | E18: 5 | F18: 4 | G18: 5 | H18: 5 | I18: Thông qua khóa học có thể hiểu rõ hơn về công việc vẫn từng làm khi lên kế hoạch, vẽ mock-up, làm việc với Code để ra được sản phẩm. Dự kiến có thể áp dụng để chi tiết hơn trong các khâu lên mock-up với design & code.
A19: 45569.658 | B19: theanh.nguyennhu@garena.vn | C19: Thế Anh | D19: BA Course 2 | E19: 4 | F19: 3 | G19: 4 | H19: 5
A20: 45572.403 | B20: thitrang.nguyen@garena.vn | C20: Trang | D20: BA Course 2 | E20: 4 | F20: 3 | G20: 3 | H20: 4 | I20: Lên kế hoạch hợp lí với list công việc cần thực hiện theo mức độ ưu tiên, biết mẹo đặt câu hỏi với các bên liên quan để làm rõ yêu cầu cho tính năng | J20: Để tăng hiệu quả, nên giao bài tập về nhà hoặc bài tập thực hành cùng 1 dạng dự án/tính năng xuyên suốt từ bài 1 đến bài cuối để các bài học có kết nối và tính thực dụng.
A21: 45572.413 | B21: theviet.nguyen@garena.vn | C21: Nguyễn Thế Việt | D21: BA Course 2 | E21: 5 | F21: 4 | G21: 4 | H21: 5 | I21: Bộ kỹ năng trong việc quản lý dự án | J21: Thực tế thì nó đang không khác gì việc thực hành trước sau đó mới học căn bản của lý thuyết. Cho dù nội dung học cải thiện được rất nhiều nhưng nếu như được thì các bài học trong đó nên đi sâu vào chuyên ngành của cty mình thì tốt hơn.
A22: 45572.483 | B22: mytram.nguyen@garena.vn | C22: Nguyễn Thị Mỹ Trâm | D22: BA Course 2 | E22: 4 | F22: 3 | G22: 4 | H22: 4 | I22: Ứng dụng Figma để dựng mock up và demo cho website, có thể áp dụng đối với các vị trí cần làm về web nhiều trong team như product | J22: nhìn chung phần nội dung của cô Nhân về quản lý dự án khá khái quát về lý thuyết nền tảng, định nghĩa, không quá mới đối với Senior, nhưng có thể hữu ích cho các bạn junior hơn
A23: 45572.485 | B23: phuongthao.dao@garena.vn | C23: Đào Phương Thảo | D23: BA Course 2 | E23: 4 | F23: 3 | G23: 3 | H23: 5 | I23: Sử dụng tool draw.io để vẽ wireframe H5 | J23: Phòng học sau 6h tối bí và nóng, bật quạt thì hơi ồn. Còn lại thì ok ạ.
A24: 45572.605 | B24: ducthao.tran@garena.vn | C24: Trần Đức Thao | D24: BA Course 2 | E24: 4 | F24: 5 | G24: 4 | H24: 5 | I24: Trước khi học một kiến thức mới thì không hiểu gì về nó nhưng học xong mới thấy nó hữu ích. Cảm ơn team HR đã hỗ trợ mọi người tiếp cận những kiến thức mới và cần thiết để phát triển bản thân. Các phần hữu ích nhất với bản thân: mô hình làm việc waterfall / agile & câu hỏi 5W1H khai thác requirement từ stakeholders | J24: Mình có học thử online ở văn phòng HCM vài buổi thì cảm giác những hôm học ở SG dễ bị miss thông tin buổi học hơn, ví dụ nhiều vấn đề về đề bài hoặc thông tin không hỏi được trực tiếp. Nếu được mình nghĩ việc gom và phân ra ở 2 văn phòng đều học offline thì sẽ tiện trong việc truyền đạt kiến thức và hiểu bài hơn.
A25: 45572.652 | B25: trongnam.nguyen@garena.vn | C25: Trọng Nam | D25: BA Course 2 | E25: 4 | F25: 4 | G25: 4 | H25: 4 | I25: Cách đặt câu hỏi để xác minh vấn đề, tìm ra những dữ liệu cần thiết để trao đổi cùng dev và xây dựng hệ thống | J25: Hiện tại chưa có
A26: 45573.651 | B26: huongly.dang@garena.vn | C26: Đặng Hương Ly | D26: BA Course 2 | E26: 4 | F26: 4 | G26: 3 | H26: 4 | I26: Phần học UI UX web và dùng Figma khá thú vị, tuy nhiên khó thực hành vì Figma khá rắc rối, nên tách ra thành 2 khóa học Phần BA thì thực ra nặng về lý thuyết và kh specifically catered cho ngành game nên cảm giác kh relevant. Những cái relevant như cách manage project thì nên dành cho các bạn junior hơn
A27: 45713.722 | B27: traanh.au@garena.vn | C27: Trà Anh | D27: Marketing Analytics | E27: 4 | F27: 4 | G27: 4 | H27: 5 | I27: Chủ yếu về tư duy, mindset - Cách tư duy ra quyết định bằng các dữ liệu - Cách đưa ra danh sách các chỉ số ảnh hưởng đến kế hoạch, dự án, quyết định của mình: chỉ số nào ảnh hưởng, tại sao lại ảnh hưởng | J27: khâu hậu cần của bên này làm không ổn lắm, lịch học thì lùi nhiều, thay đổi lịch học tới từ trung tâm thì báo sát nên khó sắp xếp công việc
A28: 45714.48 | B28: huyenanh.phan@garena.vn | C28: Phan Huyền Anh | D28: Marketing Analytics | E28: 4 | F28: 4 | G28: 3 | H28: 4 | I28: Tổng hợp lại kiến thức về phân tích dữ liệu dựa vào các dimensions và metrics khác nhau. Biết thêm 1 công cụ free để tạo báo cáo (Google Looker Studio). | J28: - Giảng viên ổn, nhiệt tình, truyền đạt dễ hiểu. - Cuối buổi yêu cầu mỗi học viên tổng kết lại 1 điều mà mình tâm đắc nhất trong buổi hôm đó -> giúp ghi nhớ kiến thức thôi cuối buổi. - BTC PMAX thiếu chuyên nghiệp. Lịch học thay đổi nhiều so với ban đầu (3 lần). Thông báo nghỉ và đổi buổi quá sát, không cho học viên đủ thời gian để sắp xếp. - Tài liệu không được gửi qua email để lưu lâu dài, chỉ được chat vào group Zalo nên trôi.
A29: 45715.448 | B29: lenam.to@garena.vn | C29: Tô Lê Nam | D29: Marketing Analytics | E29: 4 | F29: 3 | G29: 3 | H29: 5 | I29: Sau khi trải qua khóa học đã học được các công thức tính toán số liệu , cách làm 1 dashboard để theo dõi số liệu Học được tư duy và cách lấy số, từ đó đã áp dụng suy luận để lấy thêm chỉ số theo dõi hiệu quả công việc. | J29: Về trung tâm giảng dạy không chuyên nghiệp, thường xuyên thay đổi lịch học rất gấp và nội dung buổi học không đi sâu và giảng dạy và thao tác thực hành rất nhanh
A30: 45830.93 | B30: phuongthao.dao@garena.vn | C30: Đào Phương Thảo | D30: Marketing Analytics | E30: 5 | F30: 5 | G30: 3 | H30: 5 | I30: Hiểu được cách pull data và đọc hiểu data | J30: Vẫn như những khóa trước, em nghĩ giảng viên lấy 1 vài ví dụ liên quan đến ngành game thì sẽ cảm thấy hứng thú khi học hơn
A31: 45860.42 | B31: anhkhoa.nguyen@garena.vn | C31: Nguyễn Anh Khoa | D31: UI UX Foundation | E31: 5 | F31: 5 | G31: 5 | H31: 5 | I31: Vễ diagram, hiểu hơn về các cái mình làm theo bản năng | J31: Không có ạ
A32: 45873.411 | B32: caocuong.tran@garena.vn | C32: Trần Cao Cương | D32: UI UX Foundation | E32: 5 | F32: 5 | G32: 5 | H32: 5 | I32: Tôi đã thay đổi và áp dụng thực hiện các phần về copy writing, UX writing và call to actions một cách hiệu quả hơn vào dự án hiện tại. | J32: Giảng viên truyền đạt rõ ràng, mạch lạc, chau chuốt, slide rõ ràng, trực quan
A33: 45873.737 | B33: myhanh.luu@garena.vn | C33: Lưu Thị Mỹ Hạnh | D33: UI UX Foundation | E33: 5 | F33: 5 | G33: 4 | H33: 5 | I33: Cách kiến trúc thông tin và khả năng sử dụng sản phẩm | J33: Đề nghị khóa học ít lý thuyết hơn 1 chút ạ :) | K33: https://drive.google.com/open?id=1hLhNuCxNlMOdiLas2__vx_vFCUrckQLL
A34: 45880.392 | B34: quangtuan.dao@garena.vn | C34: Đào Quang Tuấn | D34: UI UX Foundation | E34: 4 | F34: 4 | G34: 4 | H34: 4 | I34: N/A | J34: Hiện tại khá ok rồi | K34: https://drive.google.com/open?id=1Lb51GKxIDUcb56Es-HWJOWVAoUx6KYw7
A35: 45880.508 | B35: thienkhoa.le@garena.vn | C35: Lê Trần Thiện Khoa | D35: UI UX Foundation | E35: 5 | F35: 5 | G35: 5 | H35: 5 | I35: Có thể vẽ wireframe nhanh và tạo prototype để cho bên design và code có thể hiểu rõ hơn user flow đi như thế nào. | J35: Tài liệu đào tạo, nội dung okay, đầy đủ, dễ hiểu. | K35: https://drive.google.com/open?id=13z5sCBz59YdVlQN7f6GUAEkML3GcHkp0
A36: 45882.511 | B36: thuanh.hotran@garena.vn | C36: Hồ Trần Thu Anh | D36: UI UX Foundation | E36: 3 | F36: 4 | G36: 3 | H36: 5 | I36: Cách sử dụng Figma như 1 công cụ để thiết kế 1 wireframe cơ bản, có thể làm ref cho các website sự kiện MKT sắp tới để làm việc với các bên dễ dàng hơn | J36: Phần nội dung lý thuyết về lịch sử và background khá dài và không áp dụng được nhiều, nếu được có thể rút gọn ngắn hơn | K36: https://drive.google.com/open?id=1zCAJL4qQjN3X5NVALCAAlL7Db-zS7dhw
A37: 45882.601 | B37: sygiap.nguyen@garena.vn | C37: Nguyễn Sỹ Giáp | D37: KPIM Data Analytics | E37: 4 | F37: 5 | G37: 5 | H37: 5 | I37: Có thể làm báo cáo khoa học hơn, dễ nhìn hơn thông qua PowerBI | J37: Chưa có | K37: https://drive.google.com/open?id=1y8k_wxF2aUObst0PI8xpYW-OaZA5rF1L
A38: 45882.606 | B38: thanhtung.luu@garena.vn | C38: Lưu Thanh Tùng | D38: KPIM Data Analytics | E38: 5 | F38: 5 | G38: 5 | H38: 5 | I38: Tạo report hoặc dashboard thông qua Excel hoặc PowerBI | J38: Cách thức truyền tải của giảng viên rất tốt, dễ tiếp thu, và cực kỳ nhiệt huyết, có nhiều buổi học vượt quá thời lượng nhưng vẫn kiên trì chia sẻ chi tiết các nội dung không cố gắng kết thúc sớm. Tài liệu đào tạo rất đầy đủ và trực quan, đặc biệt có tất cả các video hướng dẫn thực hiện các bài tập về nhà hoặc các bài kiểm tra cũng như thực hành trên lớp, giúp học viên hiểu và thực hành nhanh chóng hoặc theo dõi bài không kịp hay quên kiến thức có thể tìm và xem lại nhờ các video được chia nhỏ theo từng chủ đề, giúp rút ngắn thời gian học viên phải tự tìm tòi. | K38: https://drive.google.com/open?id=1q580jqDUb0WZb0AwOTtH9Rt5_Kyc8s_I
A39: 45882.618 | B39: khaitrien.vuu@garena.vn | C39: Vưu Khai Triển | D39: KPIM Data Analytics | E39: 5 | F39: 5 | G39: 5 | H39: 5 | I39: Các ứng dụng thực tiễn của Power BI và SQL rất hay, có thể xử lý thông tin nhanh chóng với một lượng data dữ liệu lớn. Ngoài ra, các hàm công thức nâng cao của excel cũng đa dạng, cách tạo pivot table xử lý dữ liệu, tạo biểu đồ nhanh chóng. Trong công việc, các công cụ này có thể tối ưu hóa dữ liệu nhanh chóng và chính xác | J39: - Hai giảng viên của khóa học đều rất tốt, tận tâm cho việc học và luôn on duty giải đáp cho các học viên khi không có giờ lên lớp. Hai thầy nhiệt tình, giọng nói dễ nghe, dễ hiểu và truyền đạt rất mạch lạc - Tài liệu rất đầy đủ, các video hướng dẫn chi tiết, bài học cũng đa dạng và đặc biệt là các bài học, tài liệu đều có thời lượng vĩnh viễn nên đánh giá là rất rất oke - Luôn dặn dò các học viên làm bài tập, mỗi buổi đều có record, bài đăng tổng quan chung về buổi học - Hiện tại ở vai trò CS chưa áp dụng được nhiều các công cụ này, hi vọng trong tương lai có cơ hội tiếp cận với vai trò mới thì em sẽ tham khảo thêm khóa học tương tự ạ. | K39: https://drive.google.com/open?id=1Jjl4Yp8B5m6vh48jMS_Tw0XHSpUMJW6D
A40: 45883.606 | B40: hainguyen.dao@garena.vn | C40: Đào Hải Nguyên | D40: UI UX Foundation | E40: 4 | F40: 4 | G40: 4 | H40: 4 | I40: Hiểu thêm về UX để hỗ trợ cho các thiết kế UI về sau | J40: Không có phản hồi | K40: https://drive.google.com/open?id=1K-mDgfDY0LQxsqpTQUSwEqBLbZUgkJqF
A41: 45888.622 | B41: traanh.au@garena.vn | C41: Trà Anh | D41: UI UX Foundation | E41: 5 | F41: 5 | G41: 5 | H41: 5 | I41: Học xong cảm giác góc nhìn của mình được rõ hơn. Trước đó khi làm web game thì mình chỉ tập trung trải nghiệm trên góc độ cá nhân (admin). Học xong biết cách định hướng gải dụ mình là 1 user khi vào trang web game thì mình sẽ quan tâm cái gì nhất, từ đó bắt đầu thiết kế giao diện web hợp lý với trải nghiệm hơn. Một vài quy tắc hay ho trong design. Quan trọng nhất là có tí kiến thức, sang nói chuyện với des thấy yên tâm hẳn =))) | J41: ko có | K41: https://drive.google.com/open?id=1PpENJB02_pPBAF_VgpX8HeQPHpWMe0Cu
A42: 45893.591 | B42: quanghuy.duong@garena.vn | C42: Dương Quang Huy | D42: UI UX Foundation | E42: 4 | F42: 3 | G42: 3 | H42: 4 | I42: Tổ chức FGD | J42: Không | K42: https://drive.google.com/open?id=1W3l8Y-efqVsecuu3t-YeVcyDp7g7B01j
A43: 45897.842 | B43: thieuky.tran@garena.vn | C43: Trần Thiệu Kỳ | D43: UI UX Foundation | E43: 5 | F43: 4 | G43: 3 | H43: 5 | I43: Có tư duy về UX & UI để ứng dụng vào công việc Figma cơ bản giúp dưng wireframe dễ dàng hơn | J43: Flow giảng của giảng viên khá chậm, chưa được thu hút (đặc biệt ở các chương lý thuyết). Có nhiều đoạn bị lỗi nhưng không được cắt khỏi video giảng dạy | K43: https://drive.google.com/open?id=16EOKfZREZ7a8j6ideNZ6tSUAhkpvrZPi
A44: 45897.886 | B44: hoanganh.cao@garena.vn | C44: Cao Hoàng Anh | D44: UI UX Foundation | E44: 4 | F44: 4 | G44: 5 | H44: 5 | I44: 8 nguyên tắc của Shneiderman và mô hình BJ fogg | J44: Giảng viên nói hơi chậm, nếu để tốc độ x2 thì có lẽ là vừa phải hơn. Ngoài ra đôi lúc video hơi nhòe, có thể do mạng hoặc do video gốc có chất lượng thấp | K44: https://drive.google.com/open?id=1zn9Rn-iI1mORvvg-ov0_xGrwHdczEpys
A45: 45898.623 | B45: quochung.tran@garena.vn | C45: Trần Quốc Hưng | D45: UI UX Foundation | E45: 4 | F45: 4 | G45: 4 | H45: 4 | I45: Tôi có thể góp ý và đưa ý kiến của mình vào thiết kế các website của dự án | J45: Giảng viên có kỹ năng sư phạm tốt, truyền tải bài học rõ ràng, dễ hiểu | K45: https://drive.google.com/open?id=17P_e81gaRxrsTkaVJDOQkopGzaRP5fim
A46: 45898.737 | B46: thucanh.nguyentran@garena.vn | C46: Nguyễn Trân Thục Anh | D46: UI UX Foundation | E46: 4 | F46: 4 | G46: 4 | H46: 4 | I46: Ứng dụng figma vào thiết kế web | J46: N/A
A47: 45898.739 | B47: quochuy.dinh@garena.vn | C47: Đinh Quốc Huy | D47: UI UX Foundation | E47: 5 | F47: 5 | G47: 5 | H47: 5 | I47: Cách mà người chơi tương tác với UI và những yếu tố khiến họ hài lòng | J47: Nhịp độ truyền tải nội dung kiến thức của giảng viên còn hơi đơn điệu. | K47: https://drive.google.com/open?id=1Ai-8lGYAN2VXirW7ID1t4y0Q-73U0Pof
A48: 45898.958 | B48: vietanh.than@garena.vn | C48: Thân Việt Anh | D48: UI UX Foundation | E48: 4 | F48: 3 | G48: 3 | H48: 5 | I48: Các bước khảo sát người dùng | J48: Nội dung phần đầu hơi nặng lí thuyết | K48: https://drive.google.com/open?id=1yjZOz7cdwlsIuh2zDQ5bJ5U54WvQoKjb
A49: 45900.894 | B49: phuongthao.tran@garena.vn | C49: Tran Thi Phuong Thao | D49: UI UX Foundation | E49: 4 | F49: 4 | G49: 5 | H49: 4 | I49: Khóa học giúp mình nắm được mindset của người dùng khi tương tác với sản phẩm và cách thiết kế page để tối ưu tỷ lệ chuyển đổi. Onboarding UI/UX tốt = giữ chân user qua session 1–2, giảm cost per retained user. Biết phân tích và đặt câu hỏi đúng với team dev/design thay vì feedback mơ hồ | J49: N/A | K49: https://drive.google.com/open?id=1qw_9mhHRGxaSscBkuFUa_yandrDyTbYL
A50: 45900.903 | B50: mylinh.pham@garena.vn | C50: Phạm Mỹ Linh | D50: UI UX Foundation | E50: 4 | F50: 4 | G50: 3 | H50: 5 | I50: Thiết kế web event, tool nội bộ hiệu quả hơn | J50: Tuy đoạn đầu hơi dài dòng nhưng về sau thì cũng có nhiều kiến thức bố ích. Nhưng tổng thể khóa học vẫn hơn dài, các kiến thức đó có thể trình bày 1 cách ngắn gọn hơn. | K50: https://drive.google.com/open?id=15u5gsGcvYZaU8f70jJuLRjcVZHqddpKb
A51: 45915.964 | B51: anhvu.huynh@garena.vn | C51: Huỳnh Nguyễn Anh Vũ | D51: UI UX Foundation | E51: 4 | F51: 4 | G51: 4 | H51: 4 | I51: Mình học được cách đặt người dùng làm trung tâm trong thiết kế, từ đó có thêm yếu tố key để mình ứng dụng trong công việc | J51: Thêm nhiều ví dụ thực tế từ sản phẩm quen thuộc để dễ hình dung. Bổ sung case study thất bại/thành công để rút kinh nghiệm. | K51: https://drive.google.com/open?id=1LubCjPKEdWtZF9WdrvMn_Clkj-HMiqvd
A52: 46001.659 | B52: khaitrien.vuu@garena.vn | C52: Vưu Khai Triển | D52: Khóa học tiếng Anh BC | E52: 5 | F52: 5 | G52: 5 | H52: 5 | I52: Từ vựng Tiếng Anh đa dụng, chủ đề công việc, doanh nghiệp, kinh doanh rất nhiều, có hiệu quả khi dùng giao tiếp với KH hoặc nhân viên nước ngoài | J52: Everything is perfect ạ =))) Hi vọng năm sau công ty có tiền cho em đi học tiếp :D | K52: https://drive.google.com/open?id=1C0RoRrH--h34WvWS8f9-AgUujsNeXgW4
A53: 46001.659 | B53: minhtuan.dang@garena.vn | C53: Đặng Minh Tuấn | D53: Khóa học tiếng Anh BC | E53: 5 | F53: 5 | G53: 5 | H53: 4 | I53: Có thể tự tin giao tiếp hơn và biết dùng những từ ngon trong trường hợp mình không thể biết nói gì tiếp theo. Giáo viên gần gũi thân thiện tạo cảm giác dễ chịu | J53: Việc đăng ký học và có chuyện bận đột xuất hủy lớp học không thể hoàn tín chỉ học dẫn đến mất 1 buổi không đáng có, nên việc cải thiện sẽ tốt hơn. | K53: https://drive.google.com/open?id=1vwKnj4hQJnSlHiVYSW7hTmG6yFrHpC4n
A54: 46001.661 | B54: tini.phuc@garena.vn | C54: Phúc Thị Tí Nị | D54: Khóa học tiếng Anh BC | E54: 4 | F54: 4 | G54: 4 | H54: 4 | I54: giao tiếp bằng tiếng anh | J54: không có | K54: https://drive.google.com/open?id=18xRk4eD8ImOx3zebgEM8DZ0oTu6xszTi
A55: 46003.396 | B55: congtam.cao@garena.vn | C55: Cao Công Tâm | D55: Khóa học tiếng Anh BC | E55: 5 | F55: 4 | G55: 3 | H55: 5 | I55: Khóa học giúp mình vượt qua sự ngại ngùng khi nói tiếng Anh và biết cách chọn từ phù hợp trong từng tình huống giao tiếp. Nhờ đó mình có thể giao tiếp hiệu quả hơn với khách hàng nước ngoài và nâng cao chất lượng phục vụ. | J55: Khóa học không cố định giảng viên và hơi khó để tìm thời gian lớp học phù hợp, chỉ dành cho các bạn có thể chủ động về thời gian. | K55: https://drive.google.com/open?id=1QTq83wKMkA7TMs5YYQTbQ7d8HVPaze7U
A56: 46004.773 | B56: sygiap.nguyen@garena.vn | C56: Nguyễn Sỹ Giáp | D56: Khóa học tiếng Anh BC | E56: 5 | F56: 4 | G56: 5 | H56: 5 | I56: Có thể biết thêm được nhiều từ mới, ngữ pháp, kiến thức mới liên quan đến nhiều vấn đề, lĩnh vực khác nhau cũng như cách sử dụng để miêu tả vấn đề, đề xuất công việc khi buộc sử dụng tiếng Anh, rèn được thêm sự tự tin khi sử dụng tiếng Anh nói lên ý kiến | J56: Muốn xem xét thêm về các khóa học liên quan trí tuệ nhân tạo | K56: https://drive.google.com/open?id=13KcQfV4V_bbhCOkodoe-WKJu4gvscDME
A57: 46017.594 | B57: huythanh.le@garena.vn | C57: Lê Huy Thanh | D57: Khóa học tiếng Trung | E57: 4 | F57: 4 | G57: 4 | H57: 4 | I57: Đến hiện tại học được tiếng Trung cơ bản có thể đọc hoặc nghe hiểu 1 vài nội dung cơ bản | J57: Trung tâm cung cấp đầy đủ tài liệu, giáo viên nhiệt tình. Trong thời gian tới có mong muốn tiếp tục được hỗ trợ đào tạo tiếp khóa tiếng Trung | K57: https://drive.google.com/open?id=1g2qIhM2zirgEm0zDp6N5l2SZc4uA7WxN
A58: 46017.594 | B58: maitrang.huynh@garena.vn | C58: Huỳnh Thị Mai Trang | D58: Khóa học tiếng Trung | E58: 5 | F58: 5 | G58: 5 | H58: 5 | I58: Hiện tại học được tiếng Trung cơ bản có thể đọc hoặc nghe hiểu, giao tiếp cơ bản. | J58: Giáo viên giảng dạy dễ tiếp thu, môi trường học tập tốt. Mong muốn trong tương lai được học tiếp tục để hoàn thành HSK2. | K58: https://drive.google.com/open?id=1FaItE7sCM7BEXLnpWxS5lnP5lF3JK8Z0
A59: 46021.639 | B59: trucdoan.nguyen@garena.vn | C59: Nguyễn Hoài Trúc Đoan | D59: Khóa học tiếng Trung | E59: 5 | F59: 5 | G59: 5 | H59: 5 | I59: Sau khóa học, mình đã học hỏi thêm được ngôn ngữ mới, biết thêm một số mẫu câu giao tiếp bằng tiếng Trung để có thể áp dụng trong giao tiếp cơ bản với bạn bè, đồng nghiệp,... nếu có cơ hội tiếp xúc trong tương lai. | J59: Hy vọng có thể tiếp tục có thêm các khóa đào tạo tương tự để mọi người có cơ hội học hỏi thêm và phát triển thêm kỹ năng, ngôn ngữ mới. | K59: https://drive.google.com/open?id=1gw9CavSUmPaiBpGqRU_JKhBzHkpWr_aQ

Sheet Tracking Budget
